Workbook

Sheet C. Printer
A1: No | B1: Printer Type | C1: Code | D1: Serial Number | E1: Office | F1: Condition | I1: Picture | J1: Update | K1: Remarks
A2: 1 | B2: Epson L4260 | C2: 002-B/V/2023 | D2: X8SS013782 | E2: 2nd Floor HRD | F2: ON | G2: 45117.337 | H2: YES | I2: PRINTER EPSON L4260 - X8SS013782 - 06062023.jpg
A3: 2 | B3: Epson L4260 | C3: 003-B/V/2023 | D3: X8SS013801 | E3: 3rd Floor > Yogyakarta | F3: ON | G3: 45117.337 | H3: YES | I3: PRINTER EPSON L4260 - X8SS013801 - 05062023.jpg
A4: 3 | B4: HP Laserjet Pro MFP M28w | C4: 004-B/V/2023 | D4: VNC2L14863 | E4: Simulator | F4: ON | G4: 45148.457 | H4: YES | I4: PRINTER HP LASERJETPRO MFP M28w - - 10062023.HEIC
A5: 4 | B5: Epson L4260 | C5: 005-B/V/2023 | D5: X8SS015684 | E5: Training | F5: ON | G5: YES | H5: YES | I5: EPSON L4260 - X8SS015684.jpg | J5: 45600
A6: 5 | B6: Epson L4160 | C6: 006-B/V/2023 | D6: X4E2041871 | E6: Bandung | F6: ON | G6: 45117.337 | H6: YES | I6: PRINTER EPSON L4160 - X8SS015684 - 10062023.JPG
A7: 6 | B7: ID Card Printer Zebra ZXP Series 3 | D7: Z3J190400662 | E7: Media | F7: ON | G7: 45232.43 | H7: YES | I7: Media Id Card Printer.jpg
A8: 7 | B8: ID Card Printer Zebra ZXP Series 3 | C8: 007-B/V/2023 | D8: Z3J185200725 | E8: Media | F8: ON | G8: 45232.43 | H8: YES | I8: Media Id Card Printer.jpg
A9: 8 | B9: HP Laserjet P1102 | C9: 008-B/V/2023 | D9: VNF6H48798 | E9: Marine | F9: ON | G9: 45117.337 | H9: YES | I9: HP lasertjet - P1102 hidup.jpg
A10: 9 | B10: HP Laserjet pro mfp M28 | C10: 009-B/V/2023 | D10: VNC3L14757 | E10: IT Room | F10: ON | G10: 45117.337 | H10: YES | I10: PRINTER HP LASERJETPRO MFP M28w - ITROOM - 10062023.jpg
A11: 10 | B11: Epson L4260 | C11: 010-B/V/2023 | D11: X8SS015133 | E11: Rumah Ibu (BJB Room) | F11: ON | G11: 45117.337 | H11: YES | I11: PRINTER EPSON L4260 - X8SS015133 - 15062023.jpg
A12: 11 | B12: HP Laserjet P1102 | C12: 011-B/V/2023 | D12: VNF8M48432 | E12: Susi Marine | F12: ON | G12: YES | H12: YES | I12: PRINTER HP LASERJET P1102 - VNF6H48798 - 10062023.jpeg
A13: 12 | B13: HP Laserjet P1102 | C13: 012-B/V/2023 | D13: VNF6H43758 | E13: Ticketing Nusawiru | F13: ON | G13: 45117.337 | H13: YES | I13: HP LASERJET P1102 - VNF6H43758.jpeg | J13: 45600
A14: 13 | B14: Epson L220 | C14: 013-B/V/2023 | D14: VGVK081967 | E14: Timika > Gorontalo | F14: ON | G14: 45126.47 | H14: YES | I14: PRINTER EPSON L220 - TIMIKA - 15062023.png
A15: 14 | B15: Epson L385 | C15: 014-B/V/2023 | D15: X21K00733 | E15: Merauke | F15: ON | G15: 45126.461 | H15: YES | I15: PRINTER EPSON L385 - - 11062023.jpg
A16: 15 | B16: Epson L360 | C16: 015-B/V/2023 | D16: X3GW517213 | E16: Merauke | F16: ON | G16: 45117.337 | H16: YES | I16: PRINTER EPSON L360 - X3GW517213 - 11062023.jpg
A17: 16 | B17: Epson L360 | C17: SA-BTJ-IT/002/0002 | D17: X3GW194089 | E17: Banda Aceh | F17: ON | G17: 45117.337 | H17: YES | I17: PRINTER EPSON L360 - X3GW194089 - 12062023.jpg
A18: 17 | B18: EPSON L3120 | C18: 016-B/V/2023 | D18: XAGK118374 | E18: Padang | F18: ON | G18: YES | H18: YES | I18: EPSON L3210 - XAGK118374.jpg | J18: 45600 | K18: BANDARA
A19: 19 | B19: Canon IP2770 | C19: 018-B/V/2023 | D19: KNFR83376 | E19: Malinau | F19: ON | G19: 45117.337 | H19: YES | I19: PRINTER EPSON IP2770 - - 13062023.jpeg
A20: 20 | B20: Brother DCPT310 | C20: 019-B/V/2023 | D20: E78655G9H674302 | E20: Dabo | F20: ON | G20: 45127.548 | H20: YES | I20: PRINTER BROTHER DCP T310 - DABO - 06052023.png
A21: 21 | B21: Printer HP 1102 | C21: 038-B/V/V2023 | D21: VNC3C20676 | E21: Office Medan | F21: ON | G21: 45126.308 | I21: PRINTER HP LASERJET P1102 - VNC3C20676 - 22062023.jpeg
A22: 22 | B22: Printer Boarding Pass | C22: 020-B/V/2023 | D22: NK6F002499 | E22: Hanggar Malinau | F22: ON | G22: 45117.337 | H22: YES | I22: PRINTER EPSON M129H - NK6F002499 - 13062023 .jpeg
A23: 23 | B23: PRINTER CANON MP237 | C23: SA-MKW-IT/002/0001 | D23: CN010006121499 | E23: Manokwari | F23: ON | G23: 45126.312 | H23: YES | I23: PRINTER CANON MP237 - CN010006121499 - 11062023.jpg
A24: 24 | B24: PRINTER EPSON L360 | C24: 021-B/V/2023 | D24: X3GW154660 | E24: Tarakan | F24: ON | G24: 45117.34 | H24: YES | I24: EPSON L360 - X3GW154660.jpg | J24: 45600
A25: 25 | B25: Printer Boarding Pass | C25: 042-B/V/2023 | D25: J54F015700 | E25: Tarakan | F25: ON | G25: 45126.365 | I25: PRINTER BOARDING PASS - J54F015700.jpg | J25: 45600
A26: 26 | B26: PRINTER EPSON L3210 | C26: 022-B/V/2023 | D26: X8HT001352 | E26: Makasar | F26: ON | G26: 45117.34 | H26: YES | I26: PRINTER EPSON L3210 - X8HT001352 - 13062023.png
A27: 27 | B27: PRINTER EPSON M129H | C27: 023-B/V/2023 | D27: NK6F002499 | E27: Malinau | F27: ON | G27: 45117.34 | H27: YES | I27: PRINTER EPSON M129H - NK6F002499 - 13062023 .jpeg
A28: 28 | B28: PRINTER EPSON L3110 | C28: 024-B/V/2023 | D28: X21K00733 | E28: Wamena | F28: ON | G28: 45126.463 | H28: YES | I28: PRINTER EPSON L3110 - - 13062023.jpg
A29: 29 | B29: PRINTER CANON PIXMA G2770 | C29: 025-B/V/2023 | D29: QC3-5062 | E29: MANADO | F29: ON | H29: YES | I29: PRINTER CANON PIXMA IP2770 - QC3-5062 - 14062023.jpg | J29: 45687 | K29: Ex Tanah Merah
A30: 30 | B30: PRINTER EPSON L3860 | C30: 026-B/V/2023 | D30: - | E30: Sorong | F30: ON | G30: 45149.304 | H30: YES
A31: 31 | B31: PRINTER EPSON L3216 | C31: 027-B/V/2023 | D31: X8H5005530 | E31: Kupang | F31: ON | H31: YES | I31: EPSON L3216 - X8H5005530.jpeg | J31: 45600
A32: 32 | B32: PRINTER EPSON L3256 | C32: 028-B/V/2023 | D32: X8JW013847 | E32: Halim > Dabo | F32: ON | H32: YES | I32: PRINTER EPSON L3256 - X8JW013847 - 15062023.jpg
A33: 33 | B33: PRINTER EPSON L3510 | C33: 029-B/V/2023 | D33: X5EM109457 | E33: Halim | F33: ON | H33: YES | I33: PRINTER EPSON L3150 - X5EM109457 - 15062023.jpg
A34: 34 | B34: PRINTER EPSON L3210 | C34: 030-B/V/2023 | D34: XAGK291156 | E34: Rumah Halim | F34: ON | G34: 45117.34 | H34: YES | I34: PRINTER EPSON L3110 -XAGK291156 - 19072023.jpg
A35: 35 | B35: PRINTER CANON MP237 | C35: 031-B/V/2023 | D35: CN-010-005 845 353 | E35: Sentani | F35: ON | H35: YES
A36: 36 | B36: PRINTER EPSON L3110 | C36: 040-B/V/2023 | D36: EP-017-19-0226-726 | E36: PPC Sentani | F36: ON | G36: 45126.319 | I36: PRINTER EPSON L3110 - PPC SENTANI - 22062023.jpeg
A37: 37 | B37: EPSON L3210 | C37: 041-B/V/2023 | D37: XAGK485597Q | E37: 2nd Floor | F37: ON | G37: 45126.314 | I37: PRINTER EPSON L3210 - XAGK485597Q - 22062023 .jpg
A38: 38 | B38: PRINTER L3210 | C38: 032-B/V/2023 | D38: - | E38: Dekai | F38: ON | G38: 45149.304 | H38: YES
A39: 39 | B39: Printer Panda PRJ-58B | C39: 033-B/V/2023 | D39: - | E39: Ex Hilman Cafe | F39: ON | G39: 45120.844 | H39: 45117.333 | I39: PRINTER THERMAL PANDA - HILMAN CAFE 2 - 11072023 .jpg | K39: geoffrey office
A40: 40 | B40: Printer Panda PRJ-58B | C40: 034-B/V/2023 | D40: - | E40: Ex Hilman Cafe | F40: ON | G40: 45117.337 | H40: 45117.333 | I40: PRINTER THERMAL PANDA - HILMAN CAFE 1 - 11072023 .jpg
A41: 41 | B41: Epson L4260 | C41: 035-B/V/2023 | D41: X8SS017269 | E41: Simulator | F41: ON | G41: 45121.384 | I41: PRINTER EPSON L4260 - X8SS017269 - 14072023.jpg
A42: 42 | B42: Epson L4260 | C42: 036-B/V/2023 | D42: X8SS917369 | E42: 1st Floor | F42: ON | G42: 45117.337 | I42: PRINTER EPSON L4260 - X8SS917369 - 14072023.jpg
A43: 43 | B43: Epson L4260 | C43: 037-B/V/2023 | D43: X8SS021264 | E43: SEND TO YOGYA | F43: ON | G43: 45125.619 | I43: PRINTER EPSON L4260 - X8SS021264 - 18072023.jpg | K43: ex Geoffrey Office
A44: 44 | B44: Epson L4260 | C44: 005-B/XII/2023 | D44: X8SS020020 | E44: Papua Room | F44: ON | G44: 45125.619 | I44: PRINTER EPSON L4260 - X8SS021264 - 18072023.jpg
A45: 45 | B45: Epson L4260 | C45: 001-C/III/2024 | D45: X8SS024957 | E45: Banjarmasin | F45: ON | G45: 45125.619
A46: 46 | B46: Epson L4260 | C46: 001-C/VII/2024 | D46: X8SS027085 | E46: Sentani | F46: ON | G46: 45125.619 | I46: PRINTER EPSON L4260 - X8SS027085 - 24072024.jpg
A47: 47 | B47: Epson L3210 | C47: 001-C/IX/2024 | D47: XAGKD50041 | E47: ? | F47: ON | G47: 45125.619 | I47: PRINTER L3210 - XAGKD50041.jpg
A48: 48 | B48: Epson L3210 | C48: 001-C/XI/2024 | D48: XAGKC90669 | E48: Sabu | F48: ON | G48: 45125.619 | I48: EPSON L3210 - SABU.jpeg | J48: 45600
A49: 49 | B49: Epson L3110 | C49: 002-C/XI/2024 | D49: X6NX380353 | E49: Kupang | F49: ON | G49: 45125.619 | I49: EPSON L3110 - X6NX380353.jpeg | J49: 45600
A50: 50 | B50: Epson L4260 | C50: 001-C/VIII/2024 | D50: X8SS014145 | E50: PPC Padang | F50: ON | G50: 45125.619 | K50: HANGAR
A51: 51 | B51: Epson L4260 | C51: 001-C/II/2025 | E51: Waingapu | F51: ON | J51: 45689
A52: 52 | B52: BROTHER DCP L3551 CDW | C52: 002-C/II/2025 | D52: E79051C3N310274 | E52: BJB ROOM | F52: ON | J52: 45694
A53: 53 | B53: BROTHER DCP L3551 CDW | C53: 003-C/II/2025 | D53: E79051C3N310229 | E53: 3rd Floor | F53: ON | J53: 45694
B54: BROTHER DCP L3551 CDW | C54: 004-C/II/2025 | E54: Office Halim
A55: 54 | B55: BROTHER DCP L3560 CDW | C55: 001-C/V/2025 | E55: Flying School | F55: ON | J55: 45797
A56: 55 | B56: EPSON L4260 | C56: 001-C/VIII/2025 | D56: X8SS038212 | E56: Purchasing New Store | F56: ON | J56: 45873
A57: 56 | B57: HP 1102 | C57: 001-C/X/2025 | D57: VNC6X30362 | E57: Store Hanggar Baru Nusawiru | F57: ON | J57: 45939
B64: Epson L4260 | C64: 002-B/V/2023 | D64: X8SS013782 | E64: HRD Room
B65: HP Laserjet Pro MFP M28w | C65: 004-B/V/2023 | D65: VNC2L14863 | E65: Simulator
B66: Epson L4260 | C66: 005-B/V/2023 | D66: X8SS015684 | E66: Training
B67: ID Card Printer Zebra ZXP Series 3 | C67: 007-B/V/2023 | D67: Z3J185200725 | E67: Media
B68: ID Card Printer Zebra ZXP Series 3 | C68: 006-B/V/2023 | D68: Z3J190400662 | E68: Media
B69: HP Laserjet P1102 | C69: 008-B/V/2023 | D69: VNF6H48798 | E69: Marine
B70: HP Laserjet Pro MFP M28w | C70: 009-B/V/2023 | D70: VNC3L14757 | E70: IT Room
B71: Epson L4260 | C71: 010-B/V/2023 | D71: X8SS015133 | E71: BJB Room
B72: Epson L4260 | C72: 035-B/V/2023 | D72: X8SS017269 | E72: Simulator
B73: Epson L4260 | C73: 036-B/V/2023 | D73: X8SS917369 | E73: 1st Floor
B74: Epson L4260 | C74: 005-B/XII/2023 | D74: X8SS020020 | E74: 2nd Floor
B75: Epson L4260 | C75: 003-B/V/2023 | D75: X8SS013801 | E75: Legal Room
... B81: Epson L3210 | C81: 001-C/IX/2024 | D81: XAGKD50041 | E81: Timika (Send to Pangandaran)

Sheet H. TVMonitor
A1: No | B1: Invent Name | C1: Code | D1: Use By | E1: Serial Number | F1: Condition | H1: PIC | I1: Update | J1: Updated By | K1: Note
A2: 1 | B2: MONITOR LG | C2: 001-D/VI/2023 | D2: FLIGHT FOLLOWING | E2: 9D1INJL8R500 | F2: ON | H2: Link | I2: 45094 | J2: IT SUPPORT - SYIDIQ
A3: 2 | B3: MONITOR LG | C3: 002-D/VI/2023 | D3: OCC | E3: 112INFBB127 | F3: ON | H3: link | I3: 45094 | J3: IT SUPPORT - SYIDIQ
A4: 3 | G4: 45148.455
A5: 4
A6: 5
A7: 6
A8: 7
A9: 8
A10: 9
A11: 10
A12: 11
A13: 12
A14: 13
A15: 14
A16: 15
... A88: 87
A119: =IF(#REF!="","",A118+1) -> #REF!
A120: =IF(#REF!="","",A119+1) -> #REF!
A121: =IF(#REF!="","",A120+1) -> #REF!
A122: =IF(#REF!="","",A121+1) -> #REF!
A123: =IF(#REF!="","",A122+1) -> #REF!
A124: =IF(#REF!="","",A123+1) -> #REF!
A125: =IF(#REF!="","",A124+1) -> #REF!
A126: =IF(#REF!="","",A125+1) -> #REF!
A127: =IF(#REF!="","",A126+1) -> #REF!
A128: =IF(#REF!="","",A127+1) -> #REF!
A129: =IF(#REF!="","",A128+1) -> #REF!
A130: =IF(#REF!="","",A129+1) -> #REF!
... A986: =IF(#REF!="","",A985+1) -> #REF!

Sheet 7. SIM Card
A1: No | B1: SIM Card Number | C1: User By | D1: Data Package | E1: Domestic Limit | F1: Roaming Limit | G1: Status | H1: Note
A2: 1 | B2: 62 811 211 365 | C2: Ibu Susi Pudjiastuti | D2: Halo Kick 550rb | E2: 5.000.000,00 | F2: 5.000.000 | G2: Active
A3: 2 | B3: 62 812 228 3174 | C3: Ibu Susi Pudjiastuti | D3: flash 150rb | E3: - | F3: - | G3: Active
A4: 3 | B4: 62 811 211 1070 | C4: Ibu Susi Pudjiastuti | D4: flash 75rb | E4: 300.000,00 | F4: 7.500.000 | G4: Active
A5: 4 | B5: 62 811 211 1090 | C5: Call Center - Charter | D5: flash150rb | E5: 200.000,00 | F5: - | G5: Active
A6: 5 | B6: 62 811 211 1080 | C6: Call Center - Charter | D6: flash 150rb | E6: 200.000,00 | F6: - | G6: Active
A7: 6 | B7: 62 811 211 1088 | C7: Nadine | D7: flash 150rb | E7: 1.000.000,00 | F7: 2.500.000 | G7: Active
A8: 7 | B8: 62 811 211 0398 | C8: Chief Inspector - Tatok | D8: flash150rb | E8: 300.000,00 | F8: 7.500.000 | G8: Active
A9: 8 | B9: 62 811 211 1068 | C9: Adhit | D9: flash 150rb | E9: 300.000,00 | F9: 7.500.000 | G9: Active
A10: 9 | B10: 62 811 211 1134 | C10: Ticketing Tanah Merah | D10: - | E10: 200.000,00 | F10: - | G10: Active
A11: 10 | B11: 62 811 211 1135 | C11: Ticketing Makasar | E11: - | F11: - | G11: Active
A12: 11 | B12: 62 811 211 1136 | C12: DM Sentani | D12: flash75rb | E12: 500.000,00 | F12: - | G12: Active
A13: 12 | B13: 62 811 211 1152 | C13: DM Biak (Crew : Ahmad) | D13: hvc 100rb | E13: 300.000,00 | F13: - | G13: Active
A14: 13 | B14: 62 811 211 1153 | C14: Dekai (BC:wildan) | D14: - | E14: - | F14: - | G14: Active
A15: 14 | B15: 62 811 211 3080 | C15: Call Center - Pangandaran | D15: hvc 100rb | E15: 200.000,00 | F15: - | G15: Active
A16: 15 | B16: 62 811 211 3081 | C16: Ticketing Medan | D16: - | E16: 200.000,00 | F16: - | G16: Active | H16: Pending
A17: 16 | B17: 62 811 211 3083 | C17: Santi | D17: Flash 150rb | E17: 1.000.000,00 | F17: 7.500.000 | G17: Active
A18: 17 | B18: 62 811 211 3084 | C18: Yulivia - Santi Treasury | D18: Flash 150ribu | E18: 300.000,00 | F18: 7.500.000 | G18: Active | H18: Pending
A19: 18 | B19: 62 811 211 3085 | C19: DM Tarakan | D19: Halo Kick 100rb | E19: 300.000,00 | F19: - | G19: Active
A20: 19 | B20: 62 811 211 3086 | C20: DM Samarinda ( BC: luky) | D20: Flash 150rb | E20: 300.000,00 | F20: - | G20: Active
A21: 20 | B21: 62 811 211 3087 | C21: DM Malinau (BM:Agris) | D21: Halo Kick 100rb | E21: 200.000,00 | F21: - | G21: Active
A22: 21 | B22: 62 811 211 3089 | C22: Korwil Sumatera - ada di ibu | D22: - | E22: - | F22: - | G22: Active | H22: Tidak ada Wa / Tidak Aktif
A23: 22 | B23: 62 811 211 3090 | C23: Call Center - Pangandaran | D23: - | E23: 200.000,00 | F23: 7.500.000 | G23: Active | H23: Tidak ada Wa / Pending / Dialihkan
A24: 23 | B24: 62 811 211 3091 | C24: Ibu Susi Pudjiastuti | D24: Flash 5GB 150rb | E24: 300.000,00 | F24: 7.500.000 | G24: Active
A25: 24 | B25: 62 811 211 3092 | C25: Melinasary | D25: Flash 8GB (MF 225rb) | E25: 1.000.000,00 | F25: 2.500.000 | G25: Active
A26: 25 | B26: 62 811 211 3093 | C26: Yacho | D26: Flash 150rb | E26: 500.000,00 | F26: 7.500.000 | G26: Active
A27: 26 | B27: 62 811 211 3094 | C27: Gunanjar | D27: Flash 150rb | E27: 500.000,00 | F27: 7.500.000 | G27: Active
A28: 27 | B28: 62 811 211 3095 | C28: PA ibu - Inan | D28: Flash 150rb | E28: 500.000,00 | F28: 7.500.000 | G28: Active
A29: 28 | B29: 62 811 211 3097 | C29: Indah MT | D29: Flash 150rb | E29: 300.000,00 | F29: 7.500.000 | G29: Active
A30: 29 | B30: 62 811 211 3098 | C30: CEO - pak Zulkarnaen ( Di Ibu Susi Pudjiastuti ) | D30: Flash 150ribu | E30: 5.000.000,00 | F30: 7.500.000 | G30: Active
A31: 30 | B31: 62 811 211 9888 | C31: Donny - Melati | D31: Flash 150rb | E31: 300.000,00 | F31: 7.500.000 | G31: Not Active
A32: 31 | B32: 62 811 211 6754 | C32: Tuminah | D32: Flash 75ribu | E32: 300.000,00 | F32: - | G32: Active
A33: 32 | B33: 62 811 211 6757 | C33: DM Jakarta - Nurul | D33: - | E33: 500.000,00 | F33: 7.500.000 | G33: Active | H33: Tidak ada wa/ tidak aktif
A34: 33 | B34: 62 811 211 6758 | C34: Nurul ( Korwil Papua ) | D34: - | E34: 200.000,00 | F34: - | G34: Not Active
A35: 34 | B35: 62 811 211 6759 | C35: Flight Following | D35: Flash 75rb | E35: 300.000,00 | F35: 7.500.000 | G35: Active | H35: WA/TLP
A36: 35 | B36: 62 811 211 9801 | C36: Ticketing Banjarmasin | D36: - | E36: 500.000,00 | F36: - | G36: Active | H36: Tidak ada wa / Tidak aktif
A37: 36 | B37: 62 811 211 9802 | C37: Ticketing Samarinda | D37: - | E37: 200.000,00 | F37: - | G37: Active
A38: 37 | B38: 62 811 211 9803 | C38: Operasional Muarateweh | D38: - | E38: - | F38: - | G38: Active | H38: Tidak ada wa/Tidak aktif
A39: 38 | B39: 62 811 211 9804 | C39: Ticketing Tarakan | D39: - | E39: - | F39: - | G39: Active
A40: 39 | B40: 62 811 211 9805 | C40: Ticketing Longbawan | D40: 200SMS onnet bulanan | E40: 200.000,00 | F40: - | G40: Active | H40: Only Phone
A41: 40 | B41: 62 811 211 3478 | C41: Flight Following | D41: - | E41: 0,00 | F41: - | G41: Not Active
A42: 41 | B42: 62 811 211 3631 | C42: Treasury - Neni Octaviani | D42: HaloFit MyPlan 150rb P1 | E42: 500.000,00 | F42: 2.500.000 | G42: Active
A43: 42 | B43: 62 811 212 3910 | C43: Ticketing Pagerungan | D43: Flash 75ribu | E43: 300.000,00 | F43: 7.500.000 | G43: Active | H43: Tidak ada wa / Tidak aktfi
A44: 43 | B44: 62 811 212 3915 | C44: Ricardo ( SQS ) | D44: - | E44: 500.000,00 | F44: 2.500.000 | G44: Active | H44: Berdering/Pending
A45: 44 | B45: 62 811 212 3916 | C45: Nabil ( HR Expat) > Nadia (Salary Expat) | D45: Flash 150rb | E45: 500.000,00 | F45: 7.500.000 | G45: Active | H45: Berdering/Pending
A46: 45 | B46: 62 811 212 3918 | C46: David Marwa | D46: Flash 5GB 150rb | E46: 500.000,00 | F46: 2.500.000 | G46: Not Active
A47: 46 | B47: 62 811 212 3919 | C47: Ibu Susi Pudjiastuti | D47: Flash 5GB 150rb | E47: 500.000,00 | F47: 2.500.000 | G47: Active | H47: admin expat
A48: 47 | B48: 62 811 212 3920 | C48: GA Manager | D48: - | E48: - | F48: - | G48: Not Active
A49: 48 | B49: 62 811 212 3921 | C49: Khairul ( MT Finance ) ( Account Payable ) | D49: - | E49: 200.000,00 | F49: - | G49: Active | H49: Pending
A50: 49 | B50: 62 811 212 3923 | C50: HR Manager - Madhe | D50: Flash 150rb | E50: 200.000,00 | F50: - | G50: Active
A51: 50 | B51: 62 811 212 3925 | C51: Ticketing Pangandaran | D51: - | E51: - | F51: - | G51: Not Active
A52: 51 | B52: 62 811 212 3926 | C52: Operasional Cilacap | D52: - | E52: - | F52: - | G52: Not Active
A53: 52 | B53: 62 811 212 3927 | C53: Fia ( MT Finance ) | D53: - | E53: 200.000,00 | F53: - | G53: Active
A54: 53 | B54: 62 811 212 3929 | C54: Operasional Nusawiru | D54: FLASH 75K | E54: 200.000,00 | F54: - | G54: Active
A55: 54 | B55: 62 811 212 3930 | C55: Revenue | D55: FLASH 150 | E55: 300.000,00 | F55: - | G55: Active | H55: Tidak ada wa/Pending
A56: 55 | B56: 62 811 212 3931 | C56: DM Wamena | D56: FLASH 150 | E56: 0,00 | F56: - | G56: Active
A57: 56 | B57: 62 811 212 3932 | C57: Ticketing Manokwari | D57: - | E57: 200.000,00 | F57: - | G57: Active
A58: 57 | B58: 62 811 212 3933 | C58: (OLD OCC ) Ibu Susi Pudjiastuti | D58: FLSAH 150 | E58: 300.000,00 | F58: - | G58: Active
A59: 58 | B59: 62 811 212 3934 | C59: Ticketing sorong | D59: - | E59: 200.000,00 | F59: - | G59: Active | H59: Tidak aktif
A60: 59 | B60: 62 811 212 3935 | C60: DM Merauke | D60: FLASH 150 | E60: 300.000,00 | F60: - | G60: Active
A61: 60 | B61: 62 811 212 3936 | C61: DM Timika | D61: - | E61: 200.000,00 | F61: - | G61: Active
A62: 61 | B62: 62 811 212 3937 | C62: Ticketing Timika | D62: - | E62: 200.000,00 | F62: - | G62: Active | H62: Tidak ada wa/Tidak aktif
A63: 62 | B63: 62 811 212 3939 | C63: BCC - ada di Ibu | D63: FLASH 75K | E63: 300.000,00 | F63: 7.500.000 | G63: Active
A64: 63 | B64: 62 811 212 3942 | C64: Ibu Susi Pudjiastuti | D64: FLASH 75K | E64: 300.000,00 | F64: 7.500.000 | G64: Active
A65: 64 | B65: 62 811 212 8401 | C65: IT SUPPORT - SIDIQ | D65: FLASH 150K | E65: 1.000.000,00 | F65: 7.500.000 | G65: Active
A66: 65 | B66: 62 811 212 8402 | D66: - | E66: - | F66: - | G66: Not Active
A67: 66 | B67: 62 811 212 8403 | C67: Travel Department | D67: FLASH 150K | E67: 500.000,00 | F67: 7.500.000 | G67: Active
A68: 67 | B68: 62 811 212 8404 | C68: DM Bengkulu | D68: - | E68: - | F68: - | G68: Not Active
A69: 68 | B69: 62 811 212 8405 | C69: DM Padang | D69: FLASH 150K | E69: 300.000,00 | F69: - | G69: Active
A70: 69 | B70: 62 811 212 8406 | C70: Bengkulu | D70: - | E70: 300.000,00 | F70: - | G70: Active | H70: Pending/Dialihkan
A71: 70 | B71: 62 811 212 8407 | C71: Ticketing Padang | D71: - | E71: 200.000,00 | F71: - | G71: Active
A72: 71 | B72: 62 811 212 8408 | C72: Arfin Santos - Engineering Dept Medan | D72: - | E72: - | F72: - | G72: Not Active
A73: 72 | B73: 62 811 212 8409 | C73: Ibu Susi Pudjiastuti | D73: FLASH 150K | E73: 500.000,00 | F73: - | G73: Active
A74: 73 | B74: 62 811 212 8410 | C74: Dedi Ifran | D74: - | E74: - | F74: - | G74: Not Active
A75: 74 | B75: 62 811 212 9909 | C75: HR | D75: - | E75: 300.000,00 | F75: 7.500.000 | G75: Active
A76: 75 | B76: 62 811 212 9910 | C76: Ibu Susi Pudjiastuti | D76: - | E76: 300.000,00 | F76: - | G76: Active
A77: 76 | B77: 62 811 212 9911 | C77: Ibu Susi Pudjiastuti | D77: - | E77: 300.000,00 | F77: - | G77: Active
A78: 77 | B78: 62 811 212 9912 | C78: Farid Budi Wibowo | D78: - | E78: - | F78: - | G78: Not Active
A79: 78 | B79: 62 811 212 9913 | C79: Expat & Training Departement | D79: FLASH 75K | E79: 300.000,00 | F79: 7.500.000 | G79: Active
A80: 79 | B80: 62 811 212 9916 | C80: Standby Mas Adhit - Armand 24 jan 21 | D80: - | E80: 500.000,00 | F80: 7.500.000 | G80: Rejected
A81: 80 | B81: 62 811 212 9918 | C81: Ibu Susi Pudjiastuti | D81: FLASH 75K | E81: 1.000.000,00 | F81: 2.500.000 | G81: Active
A82: 81 | B82: 62 811 212 4353 | C82: Ibu Susi Pudjiastuti | D82: FLASH 150 | E82: 500.000,00 | F82: - | G82: Active | H82: 45096.531
A83: 82 | B83: 62 811 207 9595 | C83: Ibu Susi Pudjiastuti | D83: - | E83: 200.000,00 | F83: - | G83: Not Active | H83: 45096.531
A84: 83 | B84: 62 811 207 9595 | C84: Pilot ernesto 180121 | D84: FLASH 150 | E84: 300.000,00 | F84: - | G84: Not Active
A85: 84 | B85: 62 811 207 9595 | C85: Pilot sho 180121 | D85: KICK 100K HVC | E85: 500.000,00 | F85: - | G85: Not Active
A86: 85 | B86: 62 811 207 9595 | C86: Ibu Susi Pudjiastuti - training dept 240121 | D86: FLASH 225 | E86: 300.000,00 | F86: - | G86: Active
A87: 86 | B87: 62 811 207 9595 | C87: Safety Department | D87: FLASH 150K | E87: 500.000,00 | F87: 2.500.000 | G87: Active | H87: 0811-2124-359 by Amanda
A88: 87 | B88: 62 811 212 4361 | C88: Tick Aero | D88: - | E88: - | F88: - | G88: Not Active
A89: 88 | B89: 62 811 212 7140 | C89: GA Jakarta - rumah Halim | D89: - | E89: - | F89: - | G89: Active
A90: 89 | B90: 62 811 212 7141 | C90: GA Pangandaran | D90: - | E90: - | F90: - | G90: Active
A91: 90 | B91: 62 811 212 7142 | C91: Agustina Budi Astri - Korwil Sulawesi | D91: - | E91: - | F91: - | G91: Not Active
A92: 91 | B92: 62 811 212 7143 | C92: Alvy Xavier | D92: - | E92: - | F92: - | G92: Active
A93: 92 | B93: 62 811 212 7144 | C93: Ticketing Palu | D93: - | E93: - | F93: - | G93: Active
A94: 93 | B94: 62 811 212 7145 | C94: DM Ternate | D94: - | E94: - | F94: - | G94: Active
A95: 94 | B95: 62 811 212 7146 | C95: DM Masamba | D95: - | E95: - | F95: - | G95: Active
A96: 95 | B96: 62 811 212 7147 | C96: Ticketing Masamba | D96: - | E96: - | F96: - | G96: Active | H96: tidak ada wa/ tidak aktfi
A97: 96 | B97: 62 811 212 7149 | C97: Kendari | D97: - | E97: - | F97: - | G97: Not Active
A98: 97 | B98: 62 811 212 7150 | C98: Fuji - revenue control finance | D98: - | E98: - | F98: - | G98: Active
A99: 98 | B99: 62 811 210 3192 | C99: BM Medan | D99: - | E99: - | F99: - | G99: Not Active
A100: 99 | B100: 62 811 210 3193 | C100: BM Jakarta | D100: - | E100: - | F100: - | G100: Not Active
...

Sheet 8. SIM Card (new)
B1: DATA KARTU HALO CORPORATE SUSIAIR
B3: NO | C3: NOMOR | D3: ACCOUNT NUMBER | E3: USER | F3: STATUS | G3: PAKET AKTIF | H3: BC
O4: 8112127144 | P4: PALU
B5: 1 | C5: 8112113098 | D5: 900343575 | E5: IBU (EX PAK ZULKARNAEN) | F5: AKTIF | O5: 8112123910 | P5: Unidentified (Unable to receive call) | Q5: AKTIF
B6: 2 | C6: 811211365 | D6: 902593712 | E6: IBU | F6: AKTIF | O6: 8112123936 | P6: SA TIMIKA > IT ROOM | Q6: AKTIF
B7: 3 | C7: 8112116754 | D7: 900106574 | E7: TUMINAH | F7: AKTIF | O7: 8112123937 | P7: TICKETING TIMIKA > IT ROOM | Q7: AKTIF
B8: 4 | C8: 8112116757 | D8: 900466234 | E8: DM JAKARTA | F8: AKTIF | O8: 8112124358 | P8: TANAH MERAH > IT ROOM | Q8: AKTIF
B9: 5 | C9: 8112116758 | D9: 900273403 | E9: SA NUNUKAN | F9: AKTIF | O9: 8112124357 | P9: CHIEF PILOT / SERGI | Q9: AKTIF
B10: 6 | C10: 8112116759 | D10: 900271042 | E10: FLIGHT FOLLOWING | F10: AKTIF | O10: 8112124358 | P10: TANAH MERAH > IT ROOM | Q10: AKTIF
B11: 7 | C11: 8112119801 | D11: 900591829 | E11: TICKETING BANJARMASIN | F11: AKTIF | O11: 8112128406 | P11: Unidentified (Unable to receive call) | Q11: AKTIF
B12: 8 | C12: 8112119802 | D12: 900527494 | E12: SA SAMARINDA > IT ROOM > MANADO | F12: AKTIF | O12: 8112163552 | P12: Unidentified (Unable to receive call) | Q12: AKTIF
B13: 9 | C13: 8112119803 | D13: 900344551 | E13: OPS MARATEWEH | F13: AKTIF | O13: 8112187500 | P13: Unidentified (Unable to receive call) | Q13: AKTIF
B14: 10 | C14: 8112119804 | D14: 900415217 | E14: TICKETING TARAKAN | F14: AKTIF | O14: 8112206704 | P14: Unidentified (Unable to receive call) | Q14: AKTIF
B15: 11 | C15: 8112119805 | D15: 900621721 | E15: SA LONGBAWAN | F15: AKTIF | O15: 81122300611 | P15: REISSUE 03/02/2025 to GEOFFREY | Q15: AKTIF
B16: 12 | C16: 8112119888 | D16: 900381480 | E16: MAYANG - KSP | F16: AKTIF | O16: 81122300612 | P16: CEO AMO | Q16: AKTIF
... B32: 28 | C32: 8112123936 | D32: 900754442 | E32: SA TIMIKA > IT ROOM | F32: AKTIF | O32: 8112111152 | P32: BIAK | Q32: AKTIF
B33: 29 | C33: 8112123937 | D33: 901461077 | E33: TICKETING TIMIKA > IT ROOM | F33: AKTIF | L33: R | O33: 81120030870 | P33: TIMIKA TIKETING | Q33: AKTIF
B34: 30 | C34: 8112123939 | D34: 900595610 | E34: REISSUE 05/05/2025 > GIVE TO IBU SANTI | F34: AKTIF | O34: 81120237649 | P34: HILMAN CAFE | Q34: AKTIF
B35: 31 | C35: 8112123942 | D35: 901322743 | E35: REISSUE 05/05/2025 > GIVE TO IBU SANTI | F35: AKTIF | O35: 81120040570 | P35: DATAH DAWAI > IT ROOM
B36: 32 | C36: 8112124353 | D36: 250346757 | E36: OCC | F36: AKTIF
B37: 33 | C37: 8112124354 | D37: 250346799 | E37: OCC | F37: AKTIF
B38: 34 | C38: 8112124356 | D38: 250346710 | E38: OPS MANAGER / LUKE | F38: AKTIF
B39: 35 | C39: 8112124357 | D39: 250346829 | E39: CHIEF PILOT | F39: AKTIF
B40: 36 | C40: 8112124358 | D40: 250346858 | E40: TANAH MERAH > IT ROOM | F40: AKTIF
B41: 37 | C41: 8112124359 | D41: 250346862 | E41: SQS DEPT | F41: AKTIF
B42: 38 | C42: 8112127140 | D42: 250483726 | E42: GA JAKARTA (HALIM) | F42: AKTIF
B43: 39 | C43: 8112127141 | D43: 250484548 | E43: GA PANGANDARAN | F43: AKTIF
B44: 40 | C44: 8112127143 | D44: 250484589 | E44: ALVY XAVIER | F44: AKTIF
B45: 41 | C45: 8112127144 | D45: 250484569 | E45: PALU | F45: AKTIF
B46: 42 | C46: 8112127145 | D46: 250484572 | E46: TERNATE | F46: AKTIF
B47: 43 | C47: 8112127146 | D47: 250483926 | E47: BC MASAMBA | F47: AKTIF
... B56: 52 | C56: 8112129909 | D56: 901198753 | E56: HR ADMIN | F56: AKTIF
B57: 53 | C57: 8112129910 | D57: 901224572 | E57: WATERSPORT | F57: AKTIF | I57: Susi Watersport
B58: 54 | C58: 8112129911 | D58: 901037485 | E58: MERCH | F58: AKTIF
B59: 55 | C59: 8112129913 | D59: 901150879 | E59: TRAINING ADMIN | F59: AKTIF
B60: 56 | C60: 8112129916 | D60: 901172426 | E60: ARMAND | F60: AKTIF
B61: 57 | C61: 8112129918 | D61: 901089853 | E61: REISSUE 05/05/2025 > GIVE TO IBU SANTI | F61: AKTIF
B62: 58 | C62: 8112163552 | D62: 252777921 | E62: Unidentified (Unable to receive call) | F62: AKTIF
B63: 59 | C63: 8112187500 | D63: 254932538 | E63: Unidentified (Unable to receive call) | F63: AKTIF
B64: 60 | C64: 8112206701 | D64: 683383206 | E64: SYAHRICO - LEGAL | F64: AKTIF
B65: 61 | C65: 8112206702 | D65: 683383208 | E65: TREASURY | F65: AKTIF
B66: 62 | C66: 8112206703 | D66: 683383209 | E66: BUMI SAKTI ANGKASA - PAK MIKO | F66: AKTIF
B67: 63 | C67: 8112206704 | D67: 683383210 | E67: Unidentified (Unable to receive call) | F67: AKTIF
B68: 64 | C68: 81122300611 | D68: 683691097 | E68: REISSUE 03/02/2025 | F68: AKTIF
B69: 65 | C69: 81122300612 | D69: 683692038 | E69: CEO AMO | F69: AKTIF
... B123: 119 | C123: 8112111134 | D123: 900323149 | E123: TICKETING TANAH MERAH > IT ROOM | F123: AKTIF
B124: 120 | C124: 8112111135 | D124: 683162252 | E124: TICKETING MAKASAR > TICKETING MERAUKE | F124: AKTIF | L124: R
B125: 121 | C125: 8112111136 | D125: 900252814 | E125: DM SENTANI | F125: AKTIF
B126: 122 | C126: 8112111152 | D126: 900591827 | E126: BIAK | F126: AKTIF
B127: 123 | C127: 8112111153 | D127: 683161773 | E127: DEKAI | F127: AKTIF
B128: 124 | C128: 8112113080 | D128: 900165796 | E128: CALL CENTER PANGANDARAN | F128: AKTIF
B129: 125 | C129: 8112113081 | D129: 900063004 | E129: TICKETING MEDAN | F129: AKTIF
B130: 126 | C130: 8112113083 | D130: 900042035 | E130: SANTI | F130: AKTIF
B131: 127 | C131: 8112113084 | D131: 900059610 | E131: TREASURY | F131: AKTIF
B132: 128 | C132: 8112113085 | D132: 900051405 | E132: TARAKAN | F132: AKTIF
B133: 129 | C133: 8112113086 | D133: 900024464 | E133: DM SAMARINDA > MANADO | F133: AKTIF
B134: 130 | C134: 8112113087 | D134: 900006217 | E134: DM MALINAU | F134: AKTIF
B135: 131 | C135: 8112113089 | D135: 900006299 | E135: IBU (EX INDAH KORWIL) | F135: AKTIF
B136: 132 | C136: 8112113090 | D136: 900132771 | E136: CALL CENTER PANGANDARAN | F136: AKTIF
... B142: 138 | C142: 8112113097 | D142: 900290217 | E142: PERINTIS - WINARTI | F142: AKTIF
B143: 139 | C143: 8112310239 | D143: - | E143: LEGAL IKRAMA | F143: AKTIF
B144: 140 | C144: 81120030863 | D144: - | E144: TELLO | F144: AKTIF | J144: 8114805927
B145: 141 | C145: 81120030864 | D145: - | E145: PALEMBANG | F145: AKTIF
B146: 142 | C146: 81120030865 | D146: - | E146: SURABAYA TIKETING | F146: AKTIF
B147: 143 | C147: 81120030866 | D147: - | E147: TANJUNG SELOR | F147: AKTIF
B148: 144 | C148: 81120030867 | D148: - | E148: LONG APUNG | F148: AKTIF
B149: 145 | C149: 81120030868 | D149: - | E149: WAMENA TIKETING | F149: AKTIF
B150: 146 | C150: 81120030869 | D150: - | E150: FAK FAK TIKETING > MANOKWARI | F150: AKTIF
B151: 147 | C151: 81120030870 | D151: - | E151: TIMIKA TIKETING > IT ROOM | F151: AKTIF
B152: 148 | C152: 81120030871 | D152: - | E152: LEGAL EX ZATI | F152: AKTIF
B153: 149 | C153: 81120030872 | D153: - | E153: LEGAL FEBRI | F153: AKTIF
B154: 150 | C154: 81120224612 | D154: - | E154: ALEX - REVENUE | F154: AKTIF
B155: 151 | C155: 81120224613 | D155: - | E155: SECURITY CLEARANCE | F155: AKTIF
B156: 152 | C156: 81120224614 | D156: - | E156: CHARTER PADANG | F156: AKTIF
... B182: 178 | C182: 628112163555 | D182: - | E182: IBU | F182: AKTIF
B183: 179 | C183: 628112163556 | E183: IBU | F183: AKTIF
B184: 179 | C184: 628112163557 | D184: - | E184: IBU | F184: AKTIF
B185: 180 | C185: 628112163558 | D185: - | E185: REISSUE 05/05/2025 > GIVE TO IBU SANTI | F185: AKTIF
B186: 181 | C186: 628112163559 | D186: - | E186: PAK TAQWA (Pandulaut) | F186: AKTIF
B187: 182 | C187: 628112163560 | D187: - | E187: NENI TREASURY | F187: AKTIF
B188: 183 | C188: 628112163561 | D188: - | E188: MAULANA | F188: AKTIF
B189: 184 | C189: 628112113631 | D189: - | E189: NENI | F189: AKTIF
B190: 185 | C190: 62811542899 | D190: - | E190: TICKETING MALINAU | F190: AKTIF
B191: 186 | C191: 6281120060968 | E191: PURCHASING NSW | F191: AKTIF
B192: 187 | C192: 6281120060969 | E192: HUSNI - RECEIVING INSPECTOR | F192: AKTIF
B193: 188 | C193: 6281120060970 | E193: DICKY - LOGISTIC NUSAWIRU | F193: AKTIF
B194: 189 | C194: 6281120061069 | E194: DEWI - PPC NSW | F194: AKTIF
B195: 190 | C195: 6281120061068 | E195: FARIED - CHIEF PPC | F195: AKTIF
B196: 191 | C196: 6281120058823 | E196: TICKETING WAINGAPU | F196: AKTIF
B197: 192 | C197: 6281120059064 | E197: HR AUDREY | F197: AKTIF
B198: 193 | C198: 6281129959364 | E198: HR NABILA | F198: AKTIF
B199: 194 | C199: 6281120059789 | E199: HR PAYROLL - TATI | F199: AKTIF
B200: 195 | C200: 6281120055651 | E200: ADMIN LOGISTIK | F200: AKTIF

Sheet I. SIM CARD HALO
A1: No | B1: MSISDN | C1: Name | D1: Position - Department | E1: Package
A2: 1 | B2: 811211365 | C2: IBU | D2: IBU | E2: {=_xlfn.XLOOKUP(B2,Sheet19!$A$2:$A$235,Sheet19!$B$2:$B$235)} -> Compack Enterprise Diamond Granular
A3: 2 | B3: 811542899 | C3: YULIANTI PURNAMASARI | D3: TICKETING MALINAU | E3: {=_xlfn.XLOOKUP(B3,Sheet19!$A$2:$A$235,Sheet19!$B$2:$B$235)} -> Compack Enterprise Silver Granular
A4: 3 | B4: 8112079591 | C4: LA RIZALDI | D4: BC BANJARMASIN | E4: {=_xlfn.XLOOKUP(B4,Sheet19!$A$2:$A$235,Sheet19!$B$2:$B$235)} -> Compack Enterprise Silver Granular
A5: 4 | B5: 8112079595 | C5: AZRA | D5: ASSISTANT MANAGING DIRECTOR | E5: {=_xlfn.XLOOKUP(B5,Sheet19!$A$2:$A$235,Sheet19!$B$2:$B$235)} -> Compack Enterprise Silver Granular
A6: 5 | B6: 8112079597 | C6: GEOFFREY | D6: MANAGING DIRECTOR | E6: {=_xlfn.XLOOKUP(B6,Sheet19!$A$2:$A$235,Sheet19!$B$2:$B$235)} -> Ekstra_Kuota_Berlangganan
A7: 6 | B7: 8112110398 | C7: TATOK WAHYU ENDRIANTO | D7: CHIEF INSPECTOR | E7: {=_xlfn.XLOOKUP(B7,Sheet19!$A$2:$A$235,Sheet19!$B$2:$B$235)} -> Compack Enterprise Silver Granular
A8: 7 | B8: 8112111080 | D8: CHARTER | E8: {=_xlfn.XLOOKUP(B8,Sheet19!$A$2:$A$235,Sheet19!$B$2:$B$235)} -> Compack Enterprise Silver Granular
A9: 8 | B9: 8112111088 | C9: NADINE PASCALE KAISER | D9: DIRECTOR | E9: {=_xlfn.XLOOKUP(B9,Sheet19!$A$2:$A$235,Sheet19!$B$2:$B$235)} -> Compack Enterprise Diamond Granular
A10: 9 | B10: 8112111090 | D10: CHARTER | E10: {=_xlfn.XLOOKUP(B10,Sheet19!$A$2:$A$235,Sheet19!$B$2:$B$235)} -> Compack Enterprise Silver Granular
A11: 10 | B11: 8112111136 | C11: SHANDY BAYU ERLANGGA | D11: BC SENTANI | E11: {=_xlfn.XLOOKUP(B11,Sheet19!$A$2:$A$235,Sheet19!$B$2:$B$235)} -> Compack Enterprise Silver Granular
A12: 11 | B12: 8112111152 | C12: YUSNAEDAR OKKY | D12: ALL OPS BIAK | E12: {=_xlfn.XLOOKUP(B12,Sheet19!$A$2:$A$235,Sheet19!$B$2:$B$235)} -> Compack Enterprise Silver Granular
A13: 13 | B13: 8112113081 | C13: ISMI HIDAYATUR RAHMA | D13: ADMIN MEDAN | E13: {=_xlfn.XLOOKUP(B13,Sheet19!$A$2:$A$235,Sheet19!$B$2:$B$235)} -> Compack Enterprise Silver Granular
A14: 14 | B14: 8112113083 | C14: ARI NURSANTI | D14: TREASURY MANAGER / GA MANAGER | E14: {=_xlfn.XLOOKUP(B14,Sheet19!$A$2:$A$235,Sheet19!$B$2:$B$235)} -> Compack Enterprise Silver Granular
A15: 15 | B15: 8112113084 | C15: IBU | D15: EX TREASURY YULIVIA | E15: {=_xlfn.XLOOKUP(B15,Sheet19!$A$2:$A$235,Sheet19!$B$2:$B$235)} -> Compack Enterprise Silver Granular
A16: 16 | B16: 8112113085 | C16: IQBAL ACHMAD SHALEH | D16: BC TARAKAN | E16: {=_xlfn.XLOOKUP(B16,Sheet19!$A$2:$A$235,Sheet19!$B$2:$B$235)} -> Compack Enterprise Silver Granular
A17: 17 | B17: 8112113086 | C17: MUHAMMAD IBRAHIM KHULUQIN ADZIM | D17: BC MANADO | E17: {=_xlfn.XLOOKUP(B17,Sheet19!$A$2:$A$235,Sheet19!$B$2:$B$235)} -> Compack Enterprise Silver Granular
A18: 18 | B18: 8112113087 | C18: OBET SIMON | D18: GC MALINAU | E18: {=_xlfn.XLOOKUP(B18,Sheet19!$A$2:$A$235,Sheet19!$B$2:$B$235)} -> Compack Enterprise Silver Granular
A19: 19 | B19: 8112113089 | C19: IBU (EX INDAH KORWIL) | D19: IBU | E19: {=_xlfn.XLOOKUP(B19,Sheet19!$A$2:$A$235,Sheet19!$B$2:$B$235)} -> VPN Mobile PBX Pack 4
A20: 20 | B20: 8112113091 | C20: IBU | D20: IBU | E20: {=_xlfn.XLOOKUP(B20,Sheet19!$A$2:$A$235,Sheet19!$B$2:$B$235)} -> Compack Enterprise Silver Granular
A21: 21 | B21: 8112113092 | C21: MELINASARY | D21: CHIEF OPERASIONAL | E21: {=_xlfn.XLOOKUP(B21,Sheet19!$A$2:$A$235,Sheet19!$B$2:$B$235)} -> Compack Enterprise Silver Granular
A22: 22 | B22: 8112113093 | C22: YACHO HARMAS SINAGA | D22: CORP SECRETARY | E22: {=_xlfn.XLOOKUP(B22,Sheet19!$A$2:$A$235,Sheet19!$B$2:$B$235)} -> Compack Enterprise Silver Granular
... A35: 35 | B35: 8112119805 | C35: MUHAMAD RIDWAN ASSIDIQ | D35: ALL OPS LONG BAWAN | E35: {=_xlfn.XLOOKUP(B35,Sheet19!$A$2:$A$235,Sheet19!$B$2:$B$235)} -> Compack Enterprise Silver Granular
A36: 36 | B36: 8112119888 | D36: PERSONAL ASSISTANT IBU | E36: {=_xlfn.XLOOKUP(B36,Sheet19!$A$2:$A$235,Sheet19!$B$2:$B$235)} -> Compack Enterprise Silver Granular
A37: 37 | B37: 8112123915 | C37: RICHARDO | D37: SQS MANAGER | E37: {=_xlfn.XLOOKUP(B37,Sheet19!$A$2:$A$235,Sheet19!$B$2:$B$235)} -> Compack Enterprise Silver Granular
A38: 38 | B38: 8112123916 | C38: ANITA ANGGRAINI TEDJADIPURA | D38: HR EXPAT | E38: {=_xlfn.XLOOKUP(B38,Sheet19!$A$2:$A$235,Sheet19!$B$2:$B$235)} -> Compack Enterprise Silver Granular
A39: 39 | B39: 8112123918 | C39: DAVID MAROA | D39: MAINTENANCE MANAGER | E39: {=_xlfn.XLOOKUP(B39,Sheet19!$A$2:$A$235,Sheet19!$B$2:$B$235)} -> Compack Enterprise Silver Granular
A40: 40 | B40: 8112123919 | C40: EMA RAHMAWATI | D40: EXPAT ADMIN | E40: {=_xlfn.XLOOKUP(B40,Sheet19!$A$2:$A$235,Sheet19!$B$2:$B$235)} -> Compack Enterprise Silver Granular
A41: 41 | B41: 8112123921 | C41: RISMA ARIF NUGROHO | D41: MT FINANCE | E41: {=_xlfn.XLOOKUP(B41,Sheet19!$A$2:$A$235,Sheet19!$B$2:$B$235)} -> Compack Enterprise Silver Granular
A42: 42 | B42: 8112123923 | C42: AUDREY | D42: MT HR | E42: {=_xlfn.XLOOKUP(B42,Sheet19!$A$2:$A$235,Sheet19!$B$2:$B$235)} -> Compack Enterprise Silver Granular
A43: 43 | B43: 8112123927 | C43: FIA NURALFIANI | D43: FINANCE MANAGER | E43: {=_xlfn.XLOOKUP(B43,Sheet19!$A$2:$A$235,Sheet19!$B$2:$B$235)} -> Compack Enterprise Silver Granular
A44: 44 | B44: 8112123929 | C44: SAMUEL JUNIUS | D44: GC NUSAWIRU | E44: {=_xlfn.XLOOKUP(B44,Sheet19!$A$2:$A$235,Sheet19!$B$2:$B$235)} -> Compack Enterprise Silver Granular
A45: 45 | B45: 8112123930 | C45: ANIDAH RACHMAWATI | D45: ACCOUNTING KAS DAN BANK | E45: {=_xlfn.XLOOKUP(B45,Sheet19!$A$2:$A$235,Sheet19!$B$2:$B$235)} -> Compack Enterprise Silver Granular
A46: 46 | B46: 8112123931 | C46: RIKI JULIANTO | D46: BC WAMENA | E46: {=_xlfn.XLOOKUP(B46,Sheet19!$A$2:$A$235,Sheet19!$B$2:$B$235)} -> Compack Enterprise Silver Granular
A47: 47 | B47: 8112123932 | C47: LITA NUR HARTIKA DUWILA | D47: TICKETING MANOKWARI | E47: {=_xlfn.XLOOKUP(B47,Sheet19!$A$2:$A$235,Sheet19!$B$2:$B$235)} -> Compack Enterprise Silver Granular
A48: 49 | B48: 8112123934 | C48: SUCI AZ-ZAHRA PARIOSA | D48: ADMIN SORONG | E48: {=_xlfn.XLOOKUP(B48,Sheet19!$A$2:$A$235,Sheet19!$B$2:$B$235)} -> Compack Enterprise Silver Granular
... A60: 65 | B60: 8112127150 | C60: VERA FERTIANA DEVI | D60: FINANCE | E60: {=_xlfn.XLOOKUP(B60,Sheet19!$A$2:$A$235,Sheet19!$B$2:$B$235)} -> Compack Enterprise Silver Granular
A61: 66 | B61: 8112128401 | C61: IT DEPARTMENT | D61: IT SUPPORT | E61: Halo+
A62: 67 | B62: 8112128403 | C62: GIFFARI | D62: TRAVEL | E62: {=_xlfn.XLOOKUP(B62,Sheet19!$A$2:$A$235,Sheet19!$B$2:$B$235)} -> Compack Enterprise Silver Granular
A63: 68 | B63: 8112128405 | D63: BC PADANG | E63: {=_xlfn.XLOOKUP(B63,Sheet19!$A$2:$A$235,Sheet19!$B$2:$B$235)} -> Compack Enterprise Silver Granular
A64: 69 | B64: 8112128407 | C64: PUTRI ANGGRIANA | D64: TICKETING PADANG | E64: {=_xlfn.XLOOKUP(B64,Sheet19!$A$2:$A$235,Sheet19!$B$2:$B$235)} -> Compack Enterprise Silver Granular
A65: 71 | B65: 8112129909 | C65: SEKAR GADING | D65: HR RECRUITMENT | E65: {=_xlfn.XLOOKUP(B65,Sheet19!$A$2:$A$235,Sheet19!$B$2:$B$235)} -> Compack Enterprise Silver Granular
A66: 72 | B66: 8112129910 | C66: FAZA | D66: MT GENERAL - WATERSPORT | E66: {=_xlfn.XLOOKUP(B66,Sheet19!$A$2:$A$235,Sheet19!$B$2:$B$235)} -> Compack Enterprise Silver Granular
A67: 73 | B67: 8112129911 | D67: MERCHANDISE | E67: {=_xlfn.XLOOKUP(B67,Sheet19!$A$2:$A$235,Sheet19!$B$2:$B$235)} -> Compack Enterprise Silver Granular
A68: 74 | B68: 8112129913 | C68: TIKA MUSTIKA | D68: TRAINING | E68: {=_xlfn.XLOOKUP(B68,Sheet19!$A$2:$A$235,Sheet19!$B$2:$B$235)} -> Compack Enterprise Silver Granular
A69: 75 | B69: 8112129916 | C69: ARMAND | D69: IBU | E69: {=_xlfn.XLOOKUP(B69,Sheet19!$A$2:$A$235,Sheet19!$B$2:$B$235)} -> Compack Enterprise Silver Granular
A70: 77 | B70: 8112163552 | C70: IBU | D70: IBU | E70: {=_xlfn.XLOOKUP(B70,Sheet19!$A$2:$A$235,Sheet19!$B$2:$B$235)} -> Flash 150ribu
A71: 78 | B71: 8112206701 | C71: ISNA PUTRI | D71: LEGAL | E71: {=_xlfn.XLOOKUP(B71,Sheet19!$A$2:$A$235,Sheet19!$B$2:$B$235)} -> Compack Enterprise Silver Granular
A72: 79 | B72: 8112206702 | C72: ENOK | D72: TREASURY | E72: {=_xlfn.XLOOKUP(B72,Sheet19!$A$2:$A$235,Sheet19!$B$2:$B$235)} -> Compack Enterprise Silver Granular
A73: 80 | B73: 8112206703 | C73: YULIANTO DWI JATMIKO | D73: ADMIN CV BAS | E73: {=_xlfn.XLOOKUP(B73,Sheet19!$A$2:$A$235,Sheet19!$B$2:$B$235)} -> Compack Enterprise Silver Granular
A74: 81 | B74: 8112279611 | C74: WANTORO | D74: BC SURABAYA | E74: {=_xlfn.XLOOKUP(B74,Sheet19!$A$2:$A$235,Sheet19!$B$2:$B$235)} -> Compack Enterprise Silver Granular
A75: 82 | B75: 8112279620 | C75: TUMINAH | D75: TOKEN BANK | E75: {=_xlfn.XLOOKUP(B75,Sheet19!$A$2:$A$235,Sheet19!$B$2:$B$235)} -> Compack Enterprise Silver Granular
A76: 83 | B76: 8112310238 | C76: IBU (IPAD) | D76: IBU | E76: {=_xlfn.XLOOKUP(B76,Sheet19!$A$2:$A$235,Sheet19!$B$2:$B$235)} -> Compack Enterprise Silver Granular
A77: 84 | B77: 8112310239 | C77: ICHRAMA RENGGITA EKHANANTA | D77: LEGAL | E77: {=_xlfn.XLOOKUP(B77,Sheet19!$A$2:$A$235,Sheet19!$B$2:$B$235)} -> Compack Enterprise Gold Granular
A78: 85 | B78: 8114805924 | C78: REGYFIN RIYAN YUDHA SAPUTRA | D78: TICKETING KEPI | E78: {=_xlfn.XLOOKUP(B78,Sheet19!$A$2:$A$235,Sheet19!$B$2:$B$235)} -> Compack Enterprise Silver Granular
A79: 86 | B79: 8114805925 | C79: VINSENSIA AMITA INVIOLA MEO DUE | D79: TICKETING SENTANI | E79: {=_xlfn.XLOOKUP(B79,Sheet19!$A$2:$A$235,Sheet19!$B$2:$B$235)} -> Compack Enterprise Silver Granular
A80: 87 | B80: 8114806705 | C80: NUR YAFI NAUFAL | D80: BC MANOKWARI | E80: Flash 150ribu
A81: 88 | B81: 8114806707 | C81: JUAN HARRIS YEDIDJA MALEGA | D81: BC SORONG | E81: Halo Play Medium 150rb
A82: 89 | B82: 8114806708 | C82: ABDAN SHAKUR SURYANA | D82: ALL OPS BINTUNI | E82: Compack Enterprise Silver Granular
A83: 90 | B83: 8114806715 | C83: IBU | D83: IBU | E83: Compack Enterprise Silver Granular
A84: 91 | B84: 8114806717 | D84: MAINTENANCE SENTANI | E84: Halo Kick 150rb
A85: 92 | B85: 8116138222 | C85: ADYAN MUHAMMAD HASBY | D85: BC MEDAN | E85: Halo+ 250K
A86: 93 | B86: 8116138306 | C86: NIKO REYHAN PUTRA | D86: GC GUNUNG SITOLI | E86: Compack Enterprise Silver Granular
A87: 95 | B87: 8116138333 | C87: ROHMAT YULIARDI | D87: ALL OPS BANDA ACEH | E87: Halo+ bold 80K
A88: 97 | B88: 8116177706 | C88: REINE PINGKAI GIRI ANJANI | D88: BC DABO | E88: Flash Volume 150rb
A89: 98 | B89: 8117712120 | C89: JULIO ANDREAN MORALES HAUONI | D89: BC KUPANG | E89: {=_xlfn.XLOOKUP(B89,Sheet19!$A$2:$A$235,Sheet19!$B$2:$B$235)} -> Compack Enterprise Silver Granular
A90: 99 | B90: 8122283174 | C90: DERI | D90: KSP | E90: Flash Volume 150rb
A91: 100 | B91: 81120011913 | C91: LULU HASNA SAFINATUNNAZAH | D91: TICKETING MERAUKE | E91: {=_xlfn.XLOOKUP(B91,Sheet19!$A$2:$A$235,Sheet19!$B$2:$B$235)} -> Compack Enterprise Silver Granular
A92: 101 | B92: 81120011914 | C92: INAN | D92: MODEM PORTABLE | E92: {=_xlfn.XLOOKUP(B92,Sheet19!$A$2:$A$235,Sheet19!$B$2:$B$235)} -> Compack Enterprise Silver Granular
A93: 102 | B93: 81120011915 | C93: NAJMI LAILATUL MUFIDAH | D93: ADMIN TERNATE | E93: {=_xlfn.XLOOKUP(B93,Sheet19!$A$2:$A$235,Sheet19!$B$2:$B$235)} -> Compack Enterprise Silver Granular
A94: 103 | B94: 81120011916 | C94: SAIF AL DAFFA | D94: ALL OPS SABU | E94: {=_xlfn.XLOOKUP(B94,Sheet19!$A$2:$A$235,Sheet19!$B$2:$B$235)} -> Compack Enterprise Silver Granular
A95: 104 | B95: 81120011917 | C95: RAUL HENRYAWAN | D95: ALL OPS ROTE | E95: {=_xlfn.XLOOKUP(B95,Sheet19!$A$2:$A$235,Sheet19!$B$2:$B$235)} -> Compack Enterprise Silver Granular
A96: 105 | B96: 81120011918 | C96: MUHAMMAD SETIAWAN GUSMI | D96: MARINE | E96: {=_xlfn.XLOOKUP(B96,Sheet19!$A$2:$A$235,Sheet19!$B$2:$B$235)} -> Compack Enterprise Silver Granular
A97: 106 | B97: 81120030863 | C97: MUHAMMAD FAHRI PRATAMA | D97: ALL OPS TELLO | E97: {=_xlfn.XLOOKUP(B97,Sheet19!$A$2:$A$235,Sheet19!$B$2:$B$235)} -> Compack Enterprise Gold Granular
A98: 107 | B98: 81120030865 | C98: ISAH RATNASARI | D98: TICKETING SURABAYA | E98: {=_xlfn.XLOOKUP(B98,Sheet19!$A$2:$A$235,Sheet19!$B$2:$B$235)} -> Compack Enterprise Gold Granular
A99: 108 | B99: 81120030866 | C99: HAFIZ AL AMIN | D99: ALL OPS TANJUNG SELOR | E99: {=_xlfn.XLOOKUP(B99,Sheet19!$A$2:$A$235,Sheet19!$B$2:$B$235)} -> Compack Enterprise Gold Granular
A100: 109 | B100: 81120030867 | C100: DWI INDRA | D100: GORONTALO | E100: {=_xlfn.XLOOKUP(B100,Sheet19!$A$2:$A$235,Sheet19!$B$2:$B$235)} -> Compack Enterprise Gold Granular
A101: 110 | B101: 81120030868 | C101: AGSELLA RUTH RADIANTIKA | D101: TICKETING WAMENA | E101: {=_xlfn.XLOOKUP(B101,Sheet19!$A$2:$A$235,Sheet19!$B$2:$B$235)} -> Compack Enterprise Gold Granular
A102: 112 | B102: 81120030871 | C102: EX ZATI > ICHRAMA | D102: LEGAL | E102: {=_xlfn.XLOOKUP(B102,Sheet19!$A$2:$A$235,Sheet19!$B$2:$B$235)} -> Compack Enterprise Gold Granular
A103: 113 | B103: 81120030872 | C103: MUHAMAD RAZIB | D103: LEGAL | E103: {=_xlfn.XLOOKUP(B103,Sheet19!$A$2:$A$235,Sheet19!$B$2:$B$235)} -> Compack Enterprise Gold Granular
A104: 114 | B104: 81120031421 | D104: DTU | E104: {=_xlfn.XLOOKUP(B104,Sheet19!$A$2:$A$235,Sheet19!$B$2:$B$235)} -> Compack Enterprise Silver Granular
A105: 115 | B105: 81120031468 | D105: DTU | E105: {=_xlfn.XLOOKUP(B105,Sheet19!$A$2:$A$235,Sheet19!$B$2:$B$235)} -> Compack Enterprise Silver Granular
A106: 116 | B106: 81120031469 | D106: DTU | E106: {=_xlfn.XLOOKUP(B106,Sheet19!$A$2:$A$235,Sheet19!$B$2:$B$235)} -> Compack Enterprise Silver Granular
A107: 117 | B107: 81120032026 | C107: SITI NURFAUZIAH AZMI | D107: PERINTIS | E107: {=_xlfn.XLOOKUP(B107,Sheet19!$A$2:$A$235,Sheet19!$B$2:$B$235)} -> Compack Enterprise Silver Granular
A108: 118 | B108: 81120032125 | C108: RISMA DEWI | D108: ACCOUNT PAYABLE | E108: {=_xlfn.XLOOKUP(B108,Sheet19!$A$2:$A$235,Sheet19!$B$2:$B$235)} -> Compack Enterprise Silver Granular
A109: 119 | B109: 81120032126 | C109: SENI JUNIARTI | D109: ACCOUNT PAYABLE | E109: {=_xlfn.XLOOKUP(B109,Sheet19!$A$2:$A$235,Sheet19!$B$2:$B$235)} -> Compack Enterprise Silver Granular
A110: 120 | B110: 81120032127 | C110: ANNISA ZATA | D110: ACCOUNT PAYABLE | E110: {=_xlfn.XLOOKUP(B110,Sheet19!$A$2:$A$235,Sheet19!$B$2:$B$235)} -> Compack Enterprise Silver Granular
A111: 121 | B111: 81120040519 | C111: MUHAMMAD BAMBANG KURNIAWAN | D111: GC PALANGKARAYA | E111: {=_xlfn.XLOOKUP(B111,Sheet19!$A$2:$A$235,Sheet19!$B$2:$B$235)} -> Compack Enterprise Silver Granular
A112: 122 | B112: 81120040569 | D112: TICKETING RAMPI | E112: {=_xlfn.XLOOKUP(B112,Sheet19!$A$2:$A$235,Sheet19!$B$2:$B$235)} -> Compack Enterprise Silver Granular
A113: 123 | B113: 81120041631 | C113: MARSIMIN | D113: MECHANIC | E113: {=_xlfn.XLOOKUP(B113,Sheet19!$A$2:$A$235,Sheet19!$B$2:$B$235)} -> Compack Enterprise Silver Granular
A114: 124 | B114: 81120056275 | C114: SELVI | D114: TAX | E114: {=_xlfn.XLOOKUP(B114,Sheet19!$A$2:$A$235,Sheet19!$B$2:$B$235)} -> Compack Enterprise Silver Granular
A115: 125 | B115: 81120056311 | C115: RAISANAYA | D115: FINANCE | E115: {=_xlfn.XLOOKUP(B115,Sheet19!$A$2:$A$235,Sheet19!$B$2:$B$235)} -> Compack Enterprise Silver Granular
A116: 126 | B116: 81120056312 | C116: FARREL ABYASNSAH | D116: DATA ANALYS | E116: {=_xlfn.XLOOKUP(B116,Sheet19!$A$2:$A$235,Sheet19!$B$2:$B$235)} -> Compack Enterprise Silver Granular
A117: 127 | B117: 81120056578 | C117: VANNESA WUWUNG | D117: MT REVENUE | E117: {=_xlfn.XLOOKUP(B117,Sheet19!$A$2:$A$235,Sheet19!$B$2:$B$235)} -> Compack Enterprise Silver Granular
A118: 128 | B118: 81120058823 | C118: RAHULTRI PRATAMA YARWAN | D118: ALL OPS WAINGAPU | E118: {=_xlfn.XLOOKUP(B118,Sheet19!$A$2:$A$235,Sheet19!$B$2:$B$235)} -> Compack Enterprise Silver Granular
A119: 130 | B119: 81120059789 | D119: HR | E119: {=_xlfn.XLOOKUP(B119,Sheet19!$A$2:$A$235,Sheet19!$B$2:$B$235)} -> Compack Enterprise Silver Granular
A120: 131 | B120: 81120060629 | C120: ALFYANDA FAHREZA | D120: MT VETERINARIAN | E120: {=_xlfn.XLOOKUP(B120,Sheet19!$A$2:$A$235,Sheet19!$B$2:$B$235)} -> Compack Enterprise Silver Granular
A121: 132 | B121: 81120060757 | C121: HAFZOH HAFIDZOH | D121: MT - ACCOUNT RECEIVABLE | E121: {=_xlfn.XLOOKUP(B121,Sheet19!$A$2:$A$235,Sheet19!$B$2:$B$235)} -> Compack Enterprise Silver Granular
A122: 133 | B122: 81120060969 | C122: HUSNI MUBAROK | D122: RECEIVING INSPECTOR | E122: {=_xlfn.XLOOKUP(B122,Sheet19!$A$2:$A$235,Sheet19!$B$2:$B$235)} -> Compack Enterprise Silver Granular
A123: 134 | B123: 81120060970 | C123: DICKY KRISNADI | D123: LOGISTIC | E123: {=_xlfn.XLOOKUP(B123,Sheet19!$A$2:$A$235,Sheet19!$B$2:$B$235)} -> Compack Enterprise Silver Granular
...

Sheet Sheet19
A1: Nomor | B1: Paket | C1: name
A2: 811211365 | B2: Compack Enterprise Diamond Granular | C2: {=_xlfn.XLOOKUP(A2,'I. SIM CARD HALO'!$B$2:$B$178,'I. SIM CARD HALO'!$D$2:$D$165)} -> #VALUE!
A3: 811211365 | B3: Ekstra Kuota B2B13 | C3: {=_xlfn.XLOOKUP(A3,'I. SIM CARD HALO'!$B$2:$B$178,'I. SIM CARD HALO'!$D$2:$D$165)} -> #VALUE!
A4: 811542899 | B4: Compack Enterprise Silver Granular | C4: {=_xlfn.XLOOKUP(A4,'I. SIM CARD HALO'!$B$2:$B$178,'I. SIM CARD HALO'!$D$2:$D$165)} -> #VALUE!
A5: 8111083913 | B5: Halo+_Device_Bold_Kontrak_100K | C5: {=_xlfn.XLOOKUP(A5,'I. SIM CARD HALO'!$B$2:$B$178,'I. SIM CARD HALO'!$D$2:$D$165)} -> #VALUE!
A6: 8111083913 | B6: Ekstra Kuota B2B13 | C6: {=_xlfn.XLOOKUP(A6,'I. SIM CARD HALO'!$B$2:$B$178,'I. SIM CARD HALO'!$D$2:$D$165)} -> #VALUE!
A7: 8112079591 | B7: Compack Enterprise Silver Granular | C7: {=_xlfn.XLOOKUP(A7,'I. SIM CARD HALO'!$B$2:$B$178,'I. SIM CARD HALO'!$D$2:$D$165)} -> #VALUE!
A8: 8112079591 | B8: Ekstra_Kuota_Combo | C8: {=_xlfn.XLOOKUP(A8,'I. SIM CARD HALO'!$B$2:$B$178,'I. SIM CARD HALO'!$D$2:$D$165)} -> #VALUE!
A9: 8112079592 | B9: Compack Enterprise Silver Granular | C9: {=_xlfn.XLOOKUP(A9,'I. SIM CARD HALO'!$B$2:$B$178,'I. SIM CARD HALO'!$D$2:$D$165)} -> #VALUE!
A10: 8112079592 | B10: Ekstra Kuota Data 40K | C10: {=_xlfn.XLOOKUP(A10,'I. SIM CARD HALO'!$B$2:$B$178,'I. SIM CARD HALO'!$D$2:$D$165)} -> #VALUE!
A11: 8112079595 | B11: Compack Enterprise Silver Granular | C11: {=_xlfn.XLOOKUP(A11,'I. SIM CARD HALO'!$B$2:$B$178,'I. SIM CARD HALO'!$D$2:$D$165)} -> #VALUE!
A12: 8112079597 | B12: Ekstra_Kuota_Berlangganan | C12: {=_xlfn.XLOOKUP(A12,'I. SIM CARD HALO'!$B$2:$B$178,'I. SIM CARD HALO'!$D$2:$D$165)} -> #VALUE!
A13: 8112079597 | B13: Halo_Diaspora_Western_-_Roaming | C13: {=_xlfn.XLOOKUP(A13,'I. SIM CARD HALO'!$B$2:$B$178,'I. SIM CARD HALO'!$D$2:$D$165)} -> #VALUE!
... A235: 6281323010898 | B235: Ekstra Kuota B2B13 | C235: {=_xlfn.XLOOKUP(A235,'I. SIM CARD HALO'!$B$2:$B$178,'I. SIM CARD HALO'!$D$2:$D$165)} -> #VALUE!

Sheet IP CCTV
A1: NO | B1: GEDUNG | C1: LOKASI | D1: IP CAMERA LAMA | E1: IP CAMERA BARU
A2: 1 | B2: HEAD OFFICE
A3: 2 | B3: HEAD OFFICE
A4: 3 | B4: HEAD OFFICE
A5: 4 | B5: HEAD OFFICE
A6: 5 | B6: HEAD OFFICE
A7: 6 | B7: HEAD OFFICE
A8: 7 | B8: HEAD OFFICE
A9: 8 | B9: HEAD OFFICE
A10: 9 | B10: HEAD OFFICE
A11: 10
A12: 11
A13: 12
A14: 13
A15: 14
A16: 15
A17: 16
A18: 17
A19: 18
A20: 19
A21: 20
A22: 21
A23: 22

Sheet Unknown
A1: No | B1: Laptop Type | C1: Code | D1: Serial Number | E1: Name | F1: Department | G1: Category | H1: Condition | I1: Image | J1: Doc | K1: Purchase Date | L1: Update | M1: Updated By | N1: Note | O1: Account/Passwd
A2: 1 | B2: MacBook Pro 13.3 SL/8C CPU/ 1UC GPU/8G8/512G8-ITP | C2: 003-B/III/2023 | D2: V92XVIHYYN | E2: ASKING TO INAN | L2: 45066.469 | N2: INAN DONT KNOW
A3: 2 | B3: MacBook Pro 13.3 SL/8C CPU/ 1UC GPU/8G8/512G8-ITP | C3: 005-B/III/2023 | D3: M4GYXsWTYC | E3: ASKING TO INAN | L3: 45066.479 | N3: INAN DONT KNOW
A4: 3 | B4: MacBook Pro 16 SL/12C/19C GPU/16G/512G ITP | C4: 006-B/III/2023 | D4: F446T9QQWL | E4: ASKING TO INAN | L4: 45066.457 | N4: INAN DONT KNOW
A5: 4 | B5: MacBook Air 13.6 STL/8C GPU/8GB/256GB ITP | C5: 001-B/III/2023 | D5: GK607MRW9X | H5: OFF | L5: 45066.469 | N5: MACKBOOK AIR 2022 - M2 - NFJDGVX42C
A6: 5 | B6: MacBook Pro 2019 16" Inch I9 2,3Ghz 16GB 1TB MVVK2 Gray MVVM2 Silver - MVVK2 Gray | C6: 001-A/V/2020 | E6: Alvy Xavier | K6: 43955 | L6: 45066.601 | M6: IT SUPPORT - SYIDIQ
A7: 6 | B7: MacBook Pro 2019 16" Inch I9 2,3Ghz 16GB 1TB MVVK2 Gray MVVM2 Silver - MVVM2 Silver | C7: 002-A/V/2020 | E7: Armand Hilmansyah | K7: 43956 | L7: 45066.468 | M7: IT SUPPORT - SYIDIQ
A8: 7 | B8: MacBook Pro 16 SL/12C/19C GPU/16G/512G ITP | C8: 004-B/III/2023 | D8: FQQCGJJKDF | E8: IBU | F8: RUMAH JAKARTA | L8: 45066.474 | M8: IT SUPPORT - SYIDIQ
A11: 1 | B11: Iphone 8 - Black | E11: - | O11: NO CONTACT AT HR / RESIGN
A12: 2 | B12: Iphone 8 - Black | E12: -
A13: 3 | B13: Ipad 7 2019 - Rose Gold | E13: -
A14: 4 | B14: Ipad 7 2019 - Rose Gold | E14: -
A15: 5 | B15: Ipad 7 2019 - Rose Gold | E15: -
A16: 6 | B16: Ipad 7 2019 - Rose Gold | E16: -
A17: 7 | B17: Ipad 7 2019 - Space Grey | E17: -
A18: 8 | B18: Samsung Galaxy A02 Black 3/32 | C18: 018-B/VI/2021 | E18: Mba Melly | O18: PHONE IS NOT AT MELLY
A19: 9 | B19: Samsung Galaxy A13Black 3/32 | E19: SENTANI | O19: PHONE IS NOT AT SENTANI
A20: 11 | B20: Iphone 8 - Black | E20: Nurul | O20: NO CONTACT AT HR / RESIGN
A21: 12 | B21: Ipad 7 2019 - Space Grey | E21: Email & 1stDibs | O21: EMAIL ?
A22: 5 | B22: Iphone 7 - Black | E22: Pak Budi (Kontraktor) | O22: NO CONTACT AT HR
A23: 13 | B23: Ipad 7 2019 - Rose Gold | E23: Pak Budi ( Ocean Wealth ) | O23: NO CONTACT AT HR
A24: 57 | B24: SAMSUNG GALAXY A04 - COPPER | C24: 067-B/VI/2023 | D24: R9CW6025WEB | F24: PALEMBANG | G24: ON | H24: NO | I24: 45152.324 | J24: HP SAMSUNG GALAXY A04 - R9CW6025WEB - 24072023.jpg | L24: 20/07/2023

Sheet OCC
A1: No | B1: Invent Name | C1: Code | D1: Use By | E1: Serial Number | F1: Condition | G1: Existence | H1: Image | I1: Update | J1: Updated By | K1: Note
A2: 1 | B2: LAPTOP DELL VOSTRO 14 - R5 - 8GB | D2: SIGIT - OCC | E2: 14SGYH3 | F2: ON | G2: YES | H2: Link | I2: 10 Juni 2023 | J2: IT SUPPORT - SYIDIQ
A3: 2 | B3: LAPTOP DELL VOSTRO 14 - R5 - 8GB | D3: FLIGHT FOLLOWING - OCC | E3: 9HCDYH3 | F3: ON | G3: YES | H3: link | I3: 10 Juni 2023 | J3: IT SUPPORT - SYIDIQ
A4: 3 | B4: HP REALME C2 - BLACK | D4: FLIGHT FOLLOWING - OCC | E4: RMX1941EX | F4: ON | G4: YES | H4: Link | I4: 10 Juni 2023 | J4: IT SUPPORT - SYIDIQ
A5: 4 | B5: DESKTOP LENOVO 10102 - i3 - 4GB | D5: FLIGHT FOLLOWING - OCC | E5: VS80158259 | F5: ON | G5: YES | H5: Link | I5: 10 Juni 2023 | J5: IT SUPPORT - SYIDIQ
A6: 5 | B6: DESKTOP LENOVO B320 - i3 - 8GB | D6: OCC | E6: VS50055936 | F6: ON | G6: YES | H6: Link | I6: 10 Juni 2023 | J6: IT SUPPORT - SYIDIQ
A7: 6
A8: 7
A9: 8
A10: 9
A11: 10
A12: 11
A13: 12
A14: 13
A15: 14
A16: 15
A17: 16
A18: 17
... A88: 87
A119: =IF(#REF!="","",A118+1) -> #REF!
A120: =IF(#REF!="","",A119+1) -> #REF!
A121: =IF(#REF!="","",A120+1) -> #REF!
A122: =IF(#REF!="","",A121+1) -> #REF!
A123: =IF(#REF!="","",A122+1) -> #REF!
A124: =IF(#REF!="","",A123+1) -> #REF!
A125: =IF(#REF!="","",A124+1) -> #REF!
A126: =IF(#REF!="","",A125+1) -> #REF!
A127: =IF(#REF!="","",A126+1) -> #REF!
A128: =IF(#REF!="","",A127+1) -> #REF!
A129: =IF(#REF!="","",A128+1) -> #REF!
A130: =IF(#REF!="","",A129+1) -> #REF!
... A986: =IF(#REF!="","",A985+1) -> #REF!

Sheet PR list
A1: PURCHASE REQUISITION LIST
A2: No | B2: Department | C2: Prepared By | D2: Description | E2: QTY | F2: Usage | G2: Date | I2: Note
A3: 1 | B3: HR DEPARTMENT | C3: Madhe Yanti | D3: LAPTOP | E3: 1 | F3: HR Generalis | G3: 21/06/2023 | I3: NEW LAPTOP
D4: HP | E4: 1 | F4: HR Customer Service & HR Recruitment | I4: NEW HP
D5: SIM CARD | E5: 1 | F5: HR Customer Service & HR Recruitment | I5: REISSUE 9909
D6: PC | E6: 1 | F6: HR Recruitment | I6: old pc HR
A7: 2 | B7: IT SUPPORT | C7: Mochamad Syidiq Fahrul | D7: THERMAL PASTE | E7: 1 | F7: Maintenance | G7: 15/06/2023
D8: SCREWDRIVER SET | E8: 1 | F8: Maintenance
A9: 3 | B9: MANOKWARI | C9: Ananda Cahya Kamila Aviasi | D9: HP | E9: 1 | F9: Coordinator | G9: 15/06/2023 | I9: NEW HP
A10: 4 | B10: TANAH MERAH | C10: Alfina Mika Damayanti | D10: HP | E10: 1 | F10: Ticketing | G10: 14/06/2023 | I10: NEW HP
D11: SIM CARD | E11: 1 | F11: Ticketing
A12: 5 | B12: IT SUPPORT | C12: Mochamad Syidiq Fahrul | D12: KEYBOARD SPAREPART | E12: 1 | F12: for Laptop Surabaya | G12: 45113 | I12: DONE
A13: 7 | B13: TANAH MERAH | C13: Alfina Mika Damayanti | D13: LAPTOP | E13: 1 | F13: ADMIN | G13: 24/06/2023 | H13: 45107.775 | I13: DONE
A14: 8 | B14: TARAKAN | C14: Nur Sayidah Rifqoh | D14: HP | E14: 2 | F14: TANJUNG SELOR & LONG APUNG | G14: 30/06/2023 | H14: 45107.775 | I14: DONE
A15: 9 | D15: SIM CARD | E15: 2 | F15: TANJUNG SELOR & LONG APUNG | G15: 30/06/2023 | H15: 45107.775 | I15: DONE
A16: 10 | B16: MANOKWARI | C16: Ananda Cahya Kamila Aviasi | D16: ORBIT | E16: 1 | F16: TICKETING & MESS | G16: 44992 | H16: 45110.562 | I16: TIMIKA ORBIT?
A17: 11 | B17: DABO | C17: Marfina Agustianis | D17: SERVICE COMPUTER | E17: 1 | F17: TICKETING | G17: 45084 | H17: 45117.329 | I17: DONE
A18: 12 | B18: HR | C18: Madhe Yanti | D18: PROJEKTOR | E18: 1 | F18: Nadine Office | G18: 13/07/2023 | H18: 45125.423 | I18: DONE
A19: 13 | B19: IT SUPPORT | C19: Mochamad Syidiq Fahrul | D19: PRINTER | E19: 2 | F19: Simulator & OCC | H19: 45125.424 | I19: DONE
A20: 14 | B20: IT SUPPORT | C20: Mochamad Syidiq Fahrul | D20: LAPTOP | E20: 6 | F20: - | H20: 45125.424 | I20: DONE
A21: 15 | C21: Yacho | D21: HP + SIM Card | E21: 12 | F21: Unit | G21: 18/07/2023 | H21: 45126.384 | I21: DONE
A22: 16 | C22: Request ke mba Nadine | D22: LAPTOP | E22: 1 | F22: HALIM | G22: 14/07/2023 | H22: 45148.558 | I22: 1 for SC, 1 for Rumah Tangga
A23: 17 | C23: Request ke mba Nadine | D23: LAPTOP | E23: 2 | F23: PAK MAOLIN | G23: 20/07/2023 | H23: 45148.558
A24: 18 | B24: MAKASAR | C24: Jeremy Jordan Rumi | D24: ORBIT | E24: 1 | F24: BANDARA | G24: 31/07/2023 | H24: 45148.618
A25: 19 | B25: IT SUPPORT | C25: Mochamad Syidiq Fahrul | D25: ROUTER | E25: 1 | F25: IT ROOM | G25: 45207 | H25: 45148.566
A26: 20 | B26: IT SUPPORT | C26: Mochamad Syidiq Fahrul | D26: TAPE LABEL | E26: 4 | F26: IT ROOM | G26: 45207 | H26: 45148.566
A27: 21 | B27: IT SUPPORT | C27: Mochamad Syidiq Fahrul | D27: USB HUB Converter | E27: 3 | F27: Dell XPS | G27: 45207 | H27: 45148.566
A28: 22 | B28: REVENUE | C28: LIDYA | D28: HP | E28: 1 | F28: LIDYA | H28: 45152.328
A29: 23 | B29: CHARTER | D29: PC | E29: 1 | F29: ENDAH | H29: 45152.328
A30: 24 | B30: PERINTIS | C30: Indah | D30: Charger | E30: 1
A31: 25 | B31: FLIGHT SECURITY | C31: Jodia | D31: Phone | E31: 1
A32: 26 | B32: IT SUPPORT | C32: Mochamad Syidiq Fahrul | D32: Phone | E32: 5 | F32: Stock | H32: 45174.375
A33: 27
A34: 28
A35: 29
A36: 30
A37: 31
A38: 32
A39: 33
A40: 34
A41: 35
A42: 36
A43: 37
A44: 38
... A95: 89
A119: =IF(#REF!="","",A118+1) -> #REF!
A120: =IF(#REF!="","",A119+1) -> #REF!
A121: =IF(#REF!="","",A120+1) -> #REF!
A122: =IF(#REF!="","",A121+1) -> #REF!
A123: =IF(#REF!="","",A122+1) -> #REF!
A124: =IF(#REF!="","",A123+1) -> #REF!
A125: =IF(#REF!="","",A124+1) -> #REF!
A126: =IF(#REF!="","",A125+1) -> #REF!
A127: =IF(#REF!="","",A126+1) -> #REF!
A128: =IF(#REF!="","",A127+1) -> #REF!
A129: =IF(#REF!="","",A128+1) -> #REF!
A130: =IF(#REF!="","",A129+1) -> #REF!
... A986: =IF(#REF!="","",A985+1) -> #REF!

Sheet Repairing List
A1: Repairing List
A2: No | B2: Department | C2: Description | D2: Invent | E2: Invent Code / SN | F2: Usage | G2: Date | I2: Action
A3: 1 | B3: General Affair | C3: Slow PC, Fan Noisy | D3: DESKTOP GATEWAY - INTEL PENTIUM - 2GB | E3: SA-PND-IT/001/0051 | F3: GA | G3: 19/07/2023 | H3: 45126.438 | I3: DONE
A4: 2 | B4: Accounting | C4: Cant Connect Outlook Account | D4: DESKTOP LENOVO THINKCENTRE - Intel Pentium - 2GB | E4: S1G7026 | F4: ANIDA | G4: 45206 | H4: 45126.439
A5: 3 | B5: Accounting | C5: Slow PC | D5: DESKTOP LENOVO B320
A6: 4 | B6: Accounting | C6: Install E Faktur menjadi server | D6: DESKTOP GATEWAY ZX4930 - Intel Pentium - 4GB | E6: SA-PND-IT/001/0075 | F6: YUNI | G6: 19/07/2023 | H6: 45126.57
A7: 5
A8: 6
A9: 7
A10: 8
A11: 9
A12: 10
A13: 11
A14: 12
A15: 13
A16: 14
A17: 15
A18: 16
... A76: 74
A100: =IF(#REF!="","",A99+1) -> #REF!
A101: =IF(#REF!="","",A100+1) -> #REF!
A102: =IF(#REF!="","",A101+1) -> #REF!
A103: =IF(#REF!="","",A102+1) -> #REF!
A104: =IF(#REF!="","",A103+1) -> #REF!
A105: =IF(#REF!="","",A104+1) -> #REF!
A106: =IF(#REF!="","",A105+1) -> #REF!
A107: =IF(#REF!="","",A106+1) -> #REF!
A108: =IF(#REF!="","",A107+1) -> #REF!
A109: =IF(#REF!="","",A108+1) -> #REF!
A110: =IF(#REF!="","",A109+1) -> #REF!
A111: =IF(#REF!="","",A110+1) -> #REF!
... A967: =IF(#REF!="","",A966+1) -> #REF!

Sheet TRAINING
A1: No | B1: Invent Name | C1: Code | D1: Use By | E1: Serial Number | F1: Condition | G1: Existence | H1: Image | I1: Update | J1: Updated By | K1: Note
A2: 1 | B2: DESKTOP LENOVO 10102 - i3 - 4GB | C2: SA-PND-IT/001/0107 | D2: MUTIA MAULIDA - ADMIN EXPAT | E2: VS80471834 | F2: ON | G2: YES | H2: Link | I2: 05 Juni 2023 | J2: IT SUPPORT - SYIDIQ
A3: 2 | B3: DESKTOP LENOVO - i3 - 4GB | C3: SA-PND-IT/001/0104 | D3: PUTRI RISDYA - ADMIN TRAINING | E3: VS80257632 | F3: ON | G3: YES | H3: Link | I3: 05 Juni 2023 | J3: IT SUPPORT - SYIDIQ
A4: 3 | B4: DESKTOP LENOVO IDEACENTRE B320 - i3 - 8GB | D4: CICIN - ADMIN TRAINING | E4: VS50182461 | F4: ON | G4: YES | H4: Link | I4: 05 Juni 2023 | J4: IT SUPPORT - SYIDIQ
A5: 4 | B5: DESKTOP LENOVO THINKCENTER - Intel Pentium Dual Core - 2GB | D5: EX DIKRI - ADMIN TRAINING (NO USER) | E5: S1G1817 | F5: Need Repaired | G5: YES | H5: Link | I5: 05 Juni 2023 | J5: IT SUPPORT - SYIDIQ | K5: Need Upgrade RAM
A6: 5 | B6: DESKTOP GATEWAY ZX4930 - INTEL PENTIUM - 2GB | D6: TRAINING ROOM | E6: PWG8E0200511501219300 | F6: ON | G6: YES | H6: Link | I6: 05 Juni 2023 | J6: IT SUPPORT - SYIDIQ
A7: 6 | B7: HP IPHONE 8 - BLACK | D7: CICIN - ADMIN TRAINING | E7: FFMZN9JJN1N0 | F7: ON | G7: YES | H7: Link | I7: 05 Juni 2023 | J7: IT SUPPORT - SYIDIQ
A8: 7 | B8: PRINTER EPSON L4260 | D8: TRAINING ROOM | E8: X8SS015684 | F8: ON | G8: YES | H8: Link | I8: 05 Juni 2023 | J8: IT SUPPORT - SYIDIQ
A9: 8 | B9: PROJECTOR BENQ SVGA | D9: TRAINING ROOM | E9: PDA2L01005000 | F9: ON | G9: YES | H9: Link | I9: 05 Juni 2023 | J9: IT SUPPORT - SYIDIQ
A10: 9
A11: 10
A12: 11
A13: 12
A14: 13
A15: 14
A16: 15
A17: 16
A18: 17
A19: 18
A20: 19
A21: 20
... A88: 87
A119: =IF(#REF!="","",A118+1) -> #REF!
A120: =IF(#REF!="","",A119+1) -> #REF!
A121: =IF(#REF!="","",A120+1) -> #REF!
A122: =IF(#REF!="","",A121+1) -> #REF!
A123: =IF(#REF!="","",A122+1) -> #REF!
A124: =IF(#REF!="","",A123+1) -> #REF!
A125: =IF(#REF!="","",A124+1) -> #REF!
A126: =IF(#REF!="","",A125+1) -> #REF!
A127: =IF(#REF!="","",A126+1) -> #REF!
A128: =IF(#REF!="","",A127+1) -> #REF!
A129: =IF(#REF!="","",A128+1) -> #REF!
A130: =IF(#REF!="","",A129+1) -> #REF!
... A986: =IF(#REF!="","",A985+1) -> #REF!

Sheet HO - (LT3)
A1: No | B1: Invent Name | C1: Code | D1: Use By | E1: Serial Number | F1: Condition | G1: Existence | H1: Image | I1: Update | J1: Updated By | K1: Note
A2: 1 | B2: SAMSUNG GALAXY A04 4/64 - COPPER | D2: REZKY ARYANI PUTRI - TRAVEL | E2: R9CW4015JST | F2: ON | G2: YES | H2: Link | I2: 05 Juni 2023 | J2: IT SUPPORT - SYIDIQ | K2: CHARGER
A3: 2 | B3: LAPTOP Dell XPS 13 7390 - i5-10210U - 8GB | C3: 017-B/VI/2021 | D3: MARISA HERDIANTO - CHARTER | E3: 29Z82Z2 | F3: ON | G3: YES | H3: Link | I3: 05 Juni 2023 | J3: IT SUPPORT - SYIDIQ | K3: ONLY CHARGER
A4: 3 | B4: LAPTOP Dell Vostro 3405 AMD R5 - 512GB - 8GB RAM | C4: - | D4: REZKY ARYANI PUTRI - TRAVEL | E4: 7P0VHK3 | F4: ON | G4: YES | H4: Link | I4: 05 Juni 2023 | J4: IT SUPPORT - SYIDIQ | K4: TAS + CHARGER
A5: 4 | B5: DESKTOP GATEWAY ZX4930 - INTEL PENTIUM - 4GB | D5: REZKY ARYANI PUTRI - TRAVEL | E5: PWGBE020051150124B3000 | F5: ON | G5: YES | H5: Link | I5: 05 Juni 2023 | J5: IT SUPPORT - SYIDIQ
A6: 5 | B6: LAPTOP HP PAVILION 14-DV0517 | C6: 012-B/VI/2022 | D6: NADIA WINDA DAMARANTI - HR EXPAT | E6: 5CD1379V63 | F6: ON | G6: YES | H6: Link | I6: 05 Juni 2023 | J6: IT SUPPORT - SYIDIQ | K6: CHARGER
A7: 6 | B7: LAPTOP Dell XPS 13 7390 - i5-10210U - 8GB | D7: ICHRAMA RENGGITA EKHANANTA - COMPANY LAWYER | E7: 80C7YY2 | F7: ON | G7: YES | H7: Link | I7: 05 Juni 2023 | J7: IT SUPPORT - SYIDIQ | K7: CHARGER
A8: 7 | B8: HP IPHONE X - BLACK | D8: NADIA WINDA DAMARANTI - HR EXPAT | E8: FK1XR7M6JCL8 | F8: ON | G8: YES | H8: Link | I8: 05 Juni 2023 | J8: IT SUPPORT - SYIDIQ | K8: NO CHARGER
A9: 8 | B9: HP IPHONE 8 - BLACK | D9: ICHRAMA RENGGITA EKHANANTA - COMPANY LAWYER | E9: F4HVK6B1JC67 | F9: ON | G9: YES | H9: Link | I9: 05 Juni 2023 | J9: IT SUPPORT - SYIDIQ | K9: NO CHARGER
A10: 9 | B10: HP IPHONE 8 - WHITE | D10: MARISA HERDIANTO - CHARTER | E10: FFMZC7DMN1N1 | F10: ON | G10: YES | H10: Link | I10: 05 Juni 2023 | J10: IT SUPPORT - SYIDIQ | K10: NO CHARGER
A11: 10 | B11: HP IPHONE SE - BLACK | D11: MARISA HERDIANTO - CHARTER | E11: RY6RX4TFJX | F11: ON | G11: YES | H11: Link | I11: 05 Juni 2023 | J11: IT SUPPORT - SYIDIQ | K11: NO CHARGER
A12: 11 | B12: PRINTER EPSON L4260 | D12: HO LT3 | E12: X8SS013801 | F12: ON | G12: YES | H12: Link | I12: 05 Juni 2023 | J12: IT SUPPORT - SYIDIQ
A13: 12
A14: 13
A15: 14
A16: 15
A17: 16
A18: 17
A19: 18
A20: 19
A21: 20
A22: 21
A23: 22
A24: 23
... A88: 87
A119: =IF(#REF!="","",A118+1) -> #REF!
A120: =IF(#REF!="","",A119+1) -> #REF!
A121: =IF(#REF!="","",A120+1) -> #REF!
A122: =IF(#REF!="","",A121+1) -> #REF!
A123: =IF(#REF!="","",A122+1) -> #REF!
A124: =IF(#REF!="","",A123+1) -> #REF!
A125: =IF(#REF!="","",A124+1) -> #REF!
A126: =IF(#REF!="","",A125+1) -> #REF!
A127: =IF(#REF!="","",A126+1) -> #REF!
A128: =IF(#REF!="","",A127+1) -> #REF!
A129: =IF(#REF!="","",A128+1) -> #REF!
A130: =IF(#REF!="","",A129+1) -> #REF!
... A986: =IF(#REF!="","",A985+1) -> #REF!

Sheet HO - (LT2)
A1: No | B1: Invent Name | C1: Code | D1: Use By | E1: Serial Number | F1: Condition | G1: Existence | H1: Image | I1: Update | J1: Updated By | K1: Note
A2: 1 | B2: LAPTOP DELL XPS 13 7390 - I5 11210 - 8GB | C2: 008-B/VI/2022 | D2: NUR HASAN ASYIKARI - ACCOUNTING | E2: JV3T5D3 | F2: ON | G2: YES | H2: Link | I2: 05 Juni 2023 | J2: IT SUPPORT - SYIDIQ | K2: LENGKAP
A3: 2 | B3: DESKTOP DELL INSPIRON ONE 2310 - i3 - 6GB | C3: SA-PND-IT/001/0023 | D3: SENI JUNIARTI - ACCOUNT PAYABLE | E3: 66q33p1 | F3: ON | G3: YES | H3: Link | I3: 05 Juni 2023 | J3: IT SUPPORT - SYIDIQ | K3: mouse kadang error
A4: 3 | B4: DESKTOP GATEWAY ZX4930 - Intel Pentium - 4GB | C4: SA-PND-IT/001/0071 | D4: ANIDA RACHMAWATI - ACCOUNTING | E4: PWGBE02006127024DA3000 | F4: ON | G4: YES | H4: Link | I4: 05 Juni 2023 | J4: IT SUPPORT - SYIDIQ
A5: 4 | B5: DESKTOP GATEWAY ZX4930 - Intel Pentium - 4GB | C5: SA-PND-IT/001/0074 | D5: DEDE HANI FITRIANI - ACCOUNTING | E5: PWGBE02005115012583000 | F5: ON | G5: YES | H5: Link | I5: 05 Juni 2023 | J5: IT SUPPORT - SYIDIQ
A6: 5 | B6: DESKTOP GATEWAY ZX4930 - Intel Pentium - 4GB | C6: SA-PND-IT/001/0099 | D6: NITA MAWADAH - CHASER | E6: PWGBE02005109065BF3000 | F6: ON | G6: YES | H6: Link | I6: 05 Juni 2023 | J6: IT SUPPORT - SYIDIQ
A7: 6 | B7: DESKTOP LENOVO 10102 - i3 3000 - 4GB | C7: SA-PND-IT/001/0108 | D7: NO USER (FOR BACKUP) | E7: VS80150080 | F7: ON | G7: YES | H7: Link | I7: 05 Juni 2023 | J7: IT SUPPORT - SYIDIQ
A8: 7 | B8: DESKTOP LENOVO 10102 - i3 3000 - 4GB | C8: SA-PND-IT/001/0105 | D8: RISMA DEWI - ACCOUNT PAYABLE | E8: VS80472142 | F8: ON | G8: YES | H8: Link | I8: 05 Juni 2023 | J8: IT SUPPORT - SYIDIQ
A9: 8 | B9: DESKTOP GATEWAY ZX4930 - Intel Pentium - 6GB | C9: SA-PND-IT/001/0070 | D9: VINDI AINUN AMALIASARI - ACCOUNTING | E9: PWGBE02005115012793000 | F9: ON | G9: YES | H9: Link | I9: 05 Juni 2023 | J9: IT SUPPORT - SYIDIQ
A10: 9 | B10: DESKTOP GATEWAY ZX4930 - Intel Pentium - 2GB | C10: SA-PND-IT/001/0087 | D10: SUJIUN - MARINE | E10: PWGBE02005107020793000 | F10: ON | G10: YES | H10: Link | I10: 05 Juni 2023 | J10: IT SUPPORT - SYIDIQ
A11: 10 | B11: DESKTOP GATEWAY ZX4930 - Intel Pentium - 4GB | C11: SA-PND-IT/001/0075 | D11: YUNI KURNAESIH - ACCOUNTING AND TAX | E11: PWGBE020051150122D3000 | F11: ON | G11: YES | H11: Link | I11: 05 Juni 2023 | J11: IT SUPPORT - SYIDIQ
A12: 11 | B12: DESKTOP DELL INSPIRON ONE 2310 - i3 - 6GB | C12: SA-PND-IT/001/00xx | D12: YANTI MULYANTI - ACCOUNTING | E12: 66Q23P1 | F12: ON | G12: YES | H12: Link | I12: 05 Juni 2023 | J12: IT SUPPORT - SYIDIQ
A13: 12 | B13: DESKTOP LENOVO IDEACENTRE B320 - i3 2120 - 4GB | C13: SA-PND-IT/001/0055 | D13: PUJI HANIFAH - CHASER | E13: VS50056109 | F13: ON | G13: YES | H13: Link | I13: 05 Juni 2023 | J13: IT SUPPORT - SYIDIQ
A14: 13 | B14: DESKTOP LENOVO IDEACENTRE B320 - i3 2120 - 8GB | C14: SA-PND-IT/001/0045 | D14: RENI - CHASER | E14: VS50102400 | F14: ON | G14: YES | H14: Link | I14: 05 Juni 2023 | J14: IT SUPPORT - SYIDIQ
A15: 14 | B15: LAPTOP DELL XPS 13 7390 - I5 11210 - 8GB | C15: 007/B/XI/2020 | D15: INDAH KURNIASARI - PERINTIS | E15: 3WXMYY2 | F15: ON | G15: YES | H15: Link | I15: 05 Juni 2023 | J15: IT SUPPORT - SYIDIQ
A16: 15 | B16: DESKTOP LENOVO 10102 - i3 3000 - 4GB | C16: SA-PND-IT/001/0109 | D16: WINARTI - PERINTIS | E16: VS80472124 | F16: ON | G16: YES | H16: Link | I16: 05 Juni 2023 | J16: IT SUPPORT - SYIDIQ
A17: 16 | B17: LAPTOP DELL VOSTRO 3405 AMD R5 - 512GB - 8GB RAM | D17: NENI OKTAVIANI - TREASURY | E17: CNMCYH3 | F17: ON | G17: YES | H17: Link | I17: 05 Juni 2023 | J17: IT SUPPORT - SYIDIQ
A18: 17 | B18: LAPTOP DELL INSPIRON 15 3000 - i5 - 16GB RAM | D18: MIKO YULIANTO SUJATMIKO - ADMINISTRATOR CV BAS | E18: 7FQL0H3 | F18: ON | G18: YES | H18: Link | I18: 06 Juni 2023 | J18: IT SUPPORT - SYIDIQ
A19: 18 | B19: DESKTOP LENOVO THINKCENTRE - Intel Pentium - 2GB | D19: NO USER | E19: S1G7026 | F19: OFF | G19: YES | H19: Link | I19: 06 Juni 2023 | J19: IT SUPPORT - SYIDIQ
A20: 19 | B20: HP SAMSUNG GALAXY A10S | D20: NENI OKTAVIANI - TREASURY | E20: R9CN800PV0J | F20: ON | G20: YES | H20: Link | I20: 06 Juni 2023 | J20: IT SUPPORT - SYIDIQ
A21: 20 | B21: TABLET ASUS FONEPAD 8 | D21: PUJI HANIFAH - CHASER | E21: EAOKBC108067 | F21: ON | G21: YES | H21: Link | I21: 06 Juni 2023 | J21: IT SUPPORT - SYIDIQ
A22: 21 | B22: HP NOKIA 105 | D22: PUJI HANIFAH - CHASER | E22: 357880054414531 | F22: ON | G22: YES | H22: Link | I22: 06 Juni 2023 | J22: IT SUPPORT - SYIDIQ
A23: 22 | B23: HP IPHONE 8 - BLACK | D23: INDAH KURNIASARI - PERINTIS | E23: C8QWKWZ6JC67 | F23: ON | G23: YES | H23: Link | I23: 06 Juni 2023 | J23: IT SUPPORT - SYIDIQ
A24: 23 | B24: HP SAMSUNG GALAXY A02 | D24: MIKO YULIANTO SUJATMIKO - ADMINISTRATOR CV BAS | E24: RRBR9050HEW | F24: ON | G24: YES | H24: Link | I24: 06 Juni 2023 | J24: IT SUPPORT - SYIDIQ
A25: 24 | B25: LAPTOP DELL INSPIRON 15 3521 - i3 - 4GB | D25: YANTI MULYANTI - ACCOUNTING | E25: BW551X1 | F25: ON | G25: YES | H25: Link | I25: 07 Juni 2023 | J25: IT SUPPORT - SYIDIQ
A26: 25
A27: 26
A28: 27
A29: 28
A30: 29
A31: 30
A32: 31
A33: 32
A34: 33
A35: 34
A36: 35
A37: 36
... A88: 87
A119: =IF(#REF!="","",A118+1) -> #REF!
A120: =IF(#REF!="","",A119+1) -> #REF!
A121: =IF(#REF!="","",A120+1) -> #REF!
A122: =IF(#REF!="","",A121+1) -> #REF!
A123: =IF(#REF!="","",A122+1) -> #REF!
A124: =IF(#REF!="","",A123+1) -> #REF!
A125: =IF(#REF!="","",A124+1) -> #REF!
A126: =IF(#REF!="","",A125+1) -> #REF!
A127: =IF(#REF!="","",A126+1) -> #REF!
A128: =IF(#REF!="","",A127+1) -> #REF!
A129: =IF(#REF!="","",A128+1) -> #REF!
A130: =IF(#REF!="","",A129+1) -> #REF!
... A986: =IF(#REF!="","",A985+1) -> #REF!

Sheet HRD
A1: No | B1: Invent Name | C1: Code | D1: Use By | E1: Serial Number | F1: Condition | G1: Existence | H1: Image | I1: Update | J1: Updated By | K1: Note
A2: 1 | B2: LAPTOP DELL VOSTRO 3405 AMD R5 - 512GB - 8GB RAM | D2: FITRI NUR LATIFAH RUSWANDI - RECRUITING OFFICER | E2: FDJTHK3 | F2: ON | G2: YES | H2: Link | I2: 07 Juni 2023 | J2: IT SUPPORT - SYIDIQ
A3: 2 | B3: DESKTOP DELL INSPIRON ONE 2310 - i3 - 4GB | D3: TATI SURYATI - ADMIN HR | E3: 68G33P1 | F3: ON | G3: YES | H3: Link | I3: 07 Juni 2023 | J3: IT SUPPORT - SYIDIQ
A4: 3 | B4: PRINTER EPSON L4260 | D4: HR ROOM | E4: X8SS013782 | F4: ON | G4: YES | H4: Link | I4: 07 Juni 2023 | J4: IT SUPPORT - SYIDIQ
A5: 4 | B5: LAPTOP DELL VOSTRO 3405 AMD R5 - 512GB - 8GB RAM | D5: MADE - HRD MANAGER | E5: J67GYH3 | F5: ON | G5: YES | H5: Link | I5: 09 Juni 2023 | J5: IT SUPPORT - SYIDIQ
A6: 5 | B6: HP IPHONE 8 - BLACK | D6: MADE - HRD MANAGER | E6: C8QX9K1UJC67 | F6: ON | G6: YES | H6: Link | I6: 09 Juni 2023 | J6: IT SUPPORT - SYIDIQ
A7: 6 | B7: LAPTOP DELL XPS 13 - i5 - 8GB | D7: MADE - HRD MANAGER | E7: FR1D9Y2 | F7: ON | G7: YES | H7: Link | I7: 09 Juni 2023 | J7: IT SUPPORT - SYIDIQ
A8: 7
A9: 8
A10: 9
A11: 10
A12: 11
A13: 12
A14: 13
A15: 14
A16: 15
A17: 16
A18: 17
A19: 18
... A88: 87
A119: =IF(#REF!="","",A118+1) -> #REF!
A120: =IF(#REF!="","",A119+1) -> #REF!
A121: =IF(#REF!="","",A120+1) -> #REF!
A122: =IF(#REF!="","",A121+1) -> #REF!
A123: =IF(#REF!="","",A122+1) -> #REF!
A124: =IF(#REF!="","",A123+1) -> #REF!
A125: =IF(#REF!="","",A124+1) -> #REF!
A126: =IF(#REF!="","",A125+1) -> #REF!
A127: =IF(#REF!="","",A126+1) -> #REF!
A128: =IF(#REF!="","",A127+1) -> #REF!
A129: =IF(#REF!="","",A128+1) -> #REF!
A130: =IF(#REF!="","",A129+1) -> #REF!
... A986: =IF(#REF!="","",A985+1) -> #REF!

Sheet BASE
A1: No | B1: Invent Name | C1: Code | D1: Use By | E1: Serial Number | F1: Condition | G1: Existence | H1: Image | I1: Update | J1: Updated By | K1: Note
A2: 1 | B2: DESKTOP GATEWAY ZX4930 - 3.20 GHz Intel core 2 Duo - 4GB | C2: SA-PND/190/IT/XII/2011 | D2: NUSAWIRU | E2: PWGBE02006127024CF3000 | F2: ON | G2: YES | H2: Link | I2: 10 Juni 2023 | J2: IT SUPPORT - SYIDIQ
A3: 2 | B3: HP SAMSUNG GALAXY A10s - Black | D3: NUSAWIRU | E3: R9CNB00AHLJ | F3: ON | G3: YES | H3: Link | I3: 10 Juni 2023 | J3: IT SUPPORT - SYIDIQ
A4: 3 | B4: PRINTER HP LASERJET P1102 | D4: NUSAWIRU | E4: VNF6H48798 | F4: ON | G4: YES | H4: Link | I4: 10 Juni 2023 | J4: IT SUPPORT - SYIDIQ
A5: 4 | B5: PC HP | D5: MERAUKE | E5: SGH333SONP | F5: ON | G5: YES | H5: Link | I5: 11 Juni 2023 | J5: IT SUPPORT - SYIDIQ
A6: 5 | B6: HP SAMSUNG GALAXY A10s - Black | D6: MERAUKE | E6: R9CN9001DWJ | F6: ON | G6: YES | H6: Link | I6: 11 Juni 2023 | J6: IT SUPPORT - SYIDIQ
A7: 6 | B7: PRINTER EPSON L385 | D7: MERAUKE | F7: ON | G7: YES | H7: Link | I7: 11 Juni 2023 | J7: IT SUPPORT - SYIDIQ
A8: 7 | B8: PRINTER EPSON L360 | D8: MERAUKE | E8: X3GW517213 | F8: ON | G8: YES | H8: Link | I8: 11 Juni 2023 | J8: IT SUPPORT - SYIDIQ
A9: 8 | B9: LAPTOP DELL VOSTRO 3405 AMD R5-512 GB - 8GB RAM | C9: 025-B/VI/2022 | D9: MANOKWARI | E9: 8VBBYH3 | F9: ON | G9: YES | H9: Link | I9: 11 Juni 2023 | J9: IT SUPPORT - SYIDIQ
A10: 9 | B10: HP SAMSUNG GALAXY A04 - Black | D10: MANOKWARI | E10: RR8M40RV9PY | F10: ON | G10: YES | H10: Link | I10: 11 Juni 2023 | J10: IT SUPPORT - SYIDIQ | K10: SPEAKER RUSAK
A11: 10 | B11: PRINTER CANON MP237 | C11: SA-MKW-IT/002/0001 | D11: MANOKWARI | E11: CN010006121499 | F11: ON | G11: YES | H11: Link | I11: 11 Juni 2023 | J11: IT SUPPORT - SYIDIQ
A12: 11 | B12: PC (NO-BRAND) | C12: 006/0004 SA - TRK - IT | D12: TARAKAN | F12: OFF | G12: NO | H12: Link | I12: 12 Juni 2023 | J12: IT SUPPORT - SYIDIQ
A13: 12 | B13: HP SAMSUNG GALAXY A10s - Black | D13: TARAKAN | E13: RR8M512RWBL | F13: ON | G13: YES | H13: Link | I13: 12 Juni 2023 | J13: IT SUPPORT - SYIDIQ
A14: 13 | B14: PRINTER EPSON L360 | D14: TARAKAN | E14: X3GW154660 | F14: ON | G14: YES | H14: Link | I14: 12 Juni 2023 | J14: IT SUPPORT - SYIDIQ
A15: 14 | B15: LAPTOP DELL INSPIRON 15 3421 - i3 - 4GB | C15: 032-B/V/2022 | D15: PADANG | E15: FX6GKW1 | F15: ON | G15: YES | H15: Link | I15: 12 Juni 2023 | J15: IT SUPPORT - SYIDIQ | K15: NEED REPLACE BATTERY
A16: 15 | B16: PC RAKITAN - i5 - 4GB | D16: PADANG | E16: MP1FQAZY | F16: ON | G16: YES | H16: Link | I16: 12 Juni 2023 | J16: IT SUPPORT - SYIDIQ | K16: COUNTER TICKET
A17: 16 | B17: PC RAKITAN - Core 2 Duo - 2GB | D17: PADANG | F17: ON | G17: YES | H17: Link | I17: 12 Juni 2023 | J17: IT SUPPORT - SYIDIQ
A18: 17 | B18: DESKTOP PC ALL IN ONE - i7 - 12GB | D18: PADANG | F18: ON | G18: YES | H18: Link | I18: 12 Juni 2023 | J18: IT SUPPORT - SYIDIQ
A19: 18 | B19: HP SAMSUNG GALAXY A13 | C19: 011-B/VI/2023 | D19: PADANG | E19: RR8T407PAMY | F19: ON | G19: YES | H19: Link | I19: 12 Juni 2023 | J19: IT SUPPORT - SYIDIQ
A20: 19 | B20: HP SAMSUNG GALAXY A04 | C20: 025-B-VI-2022 | D20: PADANG | E20: R9CTA006XCP | F20: ON | G20: YES | H20: Link | I20: 12 Juni 2023 | J20: IT SUPPORT - SYIDIQ
A21: 20 | B21: PRINTER EPSON L3210 | D21: PADANG | E21: XAGK118374 | F21: ON | G21: YES | H21: Link | I21: 12 Juni 2023 | J21: IT SUPPORT - SYIDIQ
A22: 21 | B22: PRINTER INK TANK 315 | D22: PADANG | E22: CNC75GODS | F22: ON | G22: YES | H22: Link | I22: 12 Juni 2023 | J22: IT SUPPORT - SYIDIQ
A23: 22 | B23: LAPTOP DELL LATITUDE 15 - 4GB | D23: MAKASAR | E23: JLW5863 | F23: ON | G23: YES | H23: Link | I23: 13 Juni 2023 | J23: IT SUPPORT - SYIDIQ
A24: 23 | B24: LAPTOP LENOVO IDEAPAD 320S - i5 | C24: 015-C/VI/2021 | D24: MAKASAR | E24: MP1DT7T5 | F24: ON | G24: YES | H24: Link | I24: 13 Juni 2023 | J24: IT SUPPORT - SYIDIQ
A25: 24 | B25: HP SAMSUNG GALAXY A04 | C25: 023-B-VI-2022 | D25: MAKASAR | E25: R9CTA02699W | F25: ON | G25: YES | H25: Link | I25: 13 Juni 2023 | J25: IT SUPPORT - SYIDIQ
A26: 25 | B26: HP SAMSUNG GALAXY A02 | C26: 003-B/VI/2023 | D26: MAKASAR | E26: RR8R709Z4QF | F26: ON | G26: YES | H26: Link | I26: 13 Juni 2023 | J26: IT SUPPORT - SYIDIQ
A27: 26 | B27: PRINTER EPSON L3210 | D27: MAKASAR | E27: X8HT001352 | F27: ON | G27: YES | H27: Link | I27: 13 Juni 2023 | J27: IT SUPPORT - SYIDIQ
A28: 27 | B28: PC RAKITAN | C28: SA-BTJ-IT-/007/0002 | D28: BANDA ACEH | E28: ZYHZH4LF200303W | F28: ON | G28: YES | H28: Link | I28: 13 Juni 2023 | J28: IT SUPPORT - SYIDIQ
A29: 28 | B29: PC RAKITAN | D29: BANDA ACEH | E29: ZTTPHMAC504752P | F29: OFF | G29: NO | H29: Link | I29: 13 Juni 2023 | J29: IT SUPPORT - SYIDIQ
A30: 29 | B30: HP SAMSUNG A10 - BLUE | C30: 099-B/VI/2023 | D30: BANDA ACEH | E30: R9CR202B8PJ | F30: ON | G30: YES | H30: Link | I30: 13 Juni 2023 | J30: IT SUPPORT - SYIDIQ
A31: 30 | B31: HP REDMI 7A - BLACK | C31: 010-B/VI/2023 | D31: BANDA ACEH | E31: M1903C3EG | F31: ON | G31: YES | H31: Link | I31: 13 Juni 2023 | J31: IT SUPPORT - SYIDIQ
A32: 31 | B32: PRINTER EPSON L360 | C32: SA-BTJ-IT/002/0002 | D32: BANDA ACEH | E32: X3GW194089 | F32: ON | G32: YES | H32: Link | I32: 13 Juni 2023 | J32: IT SUPPORT - SYIDIQ
A33: 32 | B33: LAPTOP DELL INSPIRON 15 3521 - INTEL CELERON - 2GB | D33: MALINAU | F33: ON | G33: YES | H33: Link | I33: 13 Juni 2023 | J33: IT SUPPORT - SYIDIQ
A34: 33 | B34: HP SAMSUNG GALAXY A10 | D34: MALINAU | E34: RR8M410TWYA | F34: ON | G34: YES | H34: Link | I34: 13 Juni 2023 | J34: IT SUPPORT - SYIDIQ
A35: 34 | B35: HP SAMSUNG GALAXY A01 | D35: MALINAU | E35: RR8R404590T | F35: ON | G35: YES | H35: Link | I35: 13 Juni 2023 | J35: IT SUPPORT - SYIDIQ
A36: 35 | B36: PRINTER CANON IP 2770 | D36: MALINAU | F36: ON | G36: YES | H36: Link | I36: 13 Juni 2023 | J36: IT SUPPORT - SYIDIQ
A37: 36 | B37: PRINTER EPSON M129H | D37: MALINAU | E37: NK6F002499 | F37: ON | G37: YES | H37: Link | I37: 13 Juni 2023 | J37: IT SUPPORT - SYIDIQ
A38: 40 | B38: LAPTOP DELL VOSTRO 3405 - AMD RYZEN 5 - 8GB | D38: WAMENA | E38: 7KLGHY3 | F38: ON | G38: YES | H38: Link | I38: 13 Juni 2023 | J38: IT SUPPORT - SYIDIQ
A39: 41 | B39: HP SAMSUNG GALAXY A10S - BLACK | D39: WAMENA | E39: R9CR102M2BJ | F39: ON | G39: YES | H39: Link | I39: 13 Juni 2023 | J39: IT SUPPORT - SYIDIQ
A40: 42 | B40: PRINTER EPSON L3110 | D40: WAMENA | F40: ON | G40: YES | H40: Link | I40: 13 Juni 2023 | J40: IT SUPPORT - SYIDIQ
A41: 43 | B41: LAPTOP DELL LATITUDE 15 - i3 - 4GB | C41: 010-B/V/2021 | D41: TANAH MERAH | E41: HL06863 | F41: ON | G41: YES | H41: Link | I41: 14 Juni 2023 | J41: IT SUPPORT - SYIDIQ
A42: 44 | B42: PRINTER CANON PIXMA iP2770 | D42: TANAH MERAH | E42: QC3-5062 | F42: ON | G42: YES | H42: Link | I42: 14 Juni 2023 | J42: IT SUPPORT - SYIDIQ
A43: 45 | B43: LAPTOP DELL LATITUDE 15 - i3 - 4GB | C43: 014-C/VI/2021 | D43: SORONG | E43: 6W06863 | F43: ON | G43: YES | H43: Link | I43: 13 Juni 2023 | J43: IT SUPPORT - SYIDIQ
A44: 46 | B44: HP SAMSUNG GALAXY A04 - BLACK | D44: SORONG | E44: RR8R90951LF | F44: ON | G44: YES | H44: Link | I44: 13 Juni 2023 | J44: IT SUPPORT - SYIDIQ
A45: 47 | B45: PRINTER EPSON L3860 | D45: SORONG | F45: ON | G45: YES | I45: 13 Juni 2023 | J45: IT SUPPORT - SYIDIQ
A46: 48 | B46: LAPTOP DELL VOSTRO 14 3000 - R5 - 8GB | D46: TIMIKA | E46: 1DJBYH3 | F46: ON | G46: YES | H46: Link | I46: 12 Juni 2023 | J46: IT SUPPORT - SYIDIQ
A47: 49 | B47: PRINTER EPSON L220 | D47: TIMIKA | F47: ON | G47: YES | H47: Link | I47: 12 Juni 2023 | J47: IT SUPPORT - SYIDIQ
A48: 50 | B48: PC RAKITAN | D48: TIMIKA | F48: ON | I48: 12 Juni 2023 | J48: IT SUPPORT - SYIDIQ
A49: 51 | B49: LAPTOP DELL VOSTRO 14 3000 - R5 - 8GB | C49: 022-B/VI/2022 | D49: KUPANG | E49: G37GYH3 | F49: ON | G49: YES | H49: Link | I49: 15 Juni 2023 | J49: IT SUPPORT - SYIDIQ
A50: 52 | B50: HP SAMSUNG GALAXY A13 | D50: KUPANG | E50: RR8T403239P | F50: ON | G50: YES | H50: Link | I50: 15 Juni 2023 | J50: IT SUPPORT - SYIDIQ
A51: 53 | B51: PRINTER EPSON L3210 | D51: KUPANG | E51: X8H5005530 | F51: ON | G51: YES | H51: Link | I51: 15 Juni 2023 | J51: IT SUPPORT - SYIDIQ
A52: 54 | B52: DEKSTOP PC LENOVO B320 - i3 - 2GB | D52: HALIM JAKARTA | E52: VS50055978 | F52: ON | G52: YES | H52: Link | I52: 15 Juni 2023 | J52: IT SUPPORT - SYIDIQ | K52: BANDARA
A53: 55 | B53: HP SAMSUNG GALAXY A04 | D53: HALIM JAKARTA | E53: R9CTA00MX8F | F53: ON | G53: YES | H53: Link | I53: 15 Juni 2023 | J53: IT SUPPORT - SYIDIQ | K53: BANDARA
A54: 56 | B54: PRINTER EPSON L3256 | D54: HALIM JAKARTA | E54: X8JW013847 | F54: ON | G54: YES | H54: Link | I54: 15 Juni 2023 | J54: IT SUPPORT - SYIDIQ | K54: BANDARA
A55: 57 | B55: DEKSKTOP PC LENOVO 101020 - i3 - 4GB | D55: HALIM JAKARTA | E55: VS80471831 | F55: ON | G55: YES | H55: Link | I55: 15 Juni 2023 | J55: IT SUPPORT - SYIDIQ | K55: RUMAH HALIM
A56: 58 | B56: PC DELL - INTEL COR2DUO - 4 GB | D56: HALIM JAKARTA | E56: 962QSL1 | F56: ON | G56: YES | H56: Link | I56: 15 Juni 2023 | J56: IT SUPPORT - SYIDIQ | K56: RUMAH HALIM
A57: 59 | B57: PRINTER EPSON L3510 | D57: HALIM JAKARTA | E57: X5EM109457 | F57: ON | G57: YES | H57: Link | I57: 15 Juni 2023 | J57: IT SUPPORT - SYIDIQ | K57: RUMAH HALIM
A58: 60 | B58: PRINTER EPSON L3210 | D58: HALIM JAKARTA | E58: XAGK291156 | F58: ON | G58: YES | I58: 15 Juni 2023 | J58: IT SUPPORT - SYIDIQ | K58: RUMAH HALIM
A59: 61 | B59: LAPTOP DELL INSPIRON 3421 | D59: HALIM JAKARTA | E59: 3W4FJW1 | F59: OFF | G59: NO | H59: Link | I59: 15 Juni 2023 | J59: IT SUPPORT - SYIDIQ | K59: RUMAH HALIM
A60: 62 | B60: LAPTOP DELL VOSTRO 14 3000 - R5 - 8GB | C60: 028-B-VI-2022 | D60: TIMIKA | F60: ON | G60: YES | H60: Link | I60: 15 Juni 2023 | J60: IT SUPPORT - SYIDIQ
A61: 63 | B61: HP SAMSUNG GALAXY A10 - BLUE | D61: TIMIKA | E61: RR8M512RDBJ | F61: ON | G61: YES | I61: 15 Juni 2023 | J61: IT SUPPORT - SYIDIQ
A62: 64 | B62: PRINTER EPSON L220 | D62: TIMIKA | F62: ON | G62: YES | H62: Link | I62: 15 Juni 2023 | J62: IT SUPPORT - SYIDIQ
A63: 65 | B63: PC Lenovo V530-22ICB AIO - i7, 8th Gen - 8GB | D63: SENTANI | E63: MP1FQB2W | F63: ON | G63: YES | H63: Link | I63: 17 Juni 2023 | J63: IT SUPPORT - SYIDIQ
A64: 66 | B64: PRINTER CANON MP237 | D64: SENTANI | E64: CN-010-005 845 353 | F64: ON | G64: YES | H64: Link | I64: 17 Juni 2023
A65: 67 | B65: PC - Intel Pentium G2030 - 4GB | D65: SENTANI | E65: ZYHZH4LF109866A | F65: ON | G65: YES | H65: Link | I65: 17 Juni 2023
A66: 68
A67: 69
A68: 70
A69: 71
A70: 72
A71: 73
A72: 74
A73: 75
A74: 76
A75: 77
A76: 78
A77: 79
... A85: 87
A116: =IF(#REF!="","",A115+1) -> #REF!
A117: =IF(#REF!="","",A116+1) -> #REF!
A118: =IF(#REF!="","",A117+1) -> #REF!
A119: =IF(#REF!="","",A118+1) -> #REF!
A120: =IF(#REF!="","",A119+1) -> #REF!
A121: =IF(#REF!="","",A120+1) -> #REF!
A122: =IF(#REF!="","",A121+1) -> #REF!
A123: =IF(#REF!="","",A122+1) -> #REF!
A124: =IF(#REF!="","",A123+1) -> #REF!
A125: =IF(#REF!="","",A124+1) -> #REF!
A126: =IF(#REF!="","",A125+1) -> #REF!
A127: =IF(#REF!="","",A126+1) -> #REF!
... A983: =IF(#REF!="","",A982+1) -> #REF!

Sheet MEDIA
A1: No | B1: Invent Name | C1: Code | D1: Use By | E1: Serial Number | F1: Condition | G1: Existence | H1: Image | I1: Update | J1: Updated By | K1: Note
A2: 1 | B2: LAPTOP DELL XPS 13 7390 - i5 - 8GB | D2: SEKAR - MEDIA | E2: BX611J3 | F2: ON | G2: YES | H2: Link | I2: 03 Juni 2023 | J2: IT SUPPORT - SYIDIQ | K2: EX NANTA
A3: 2 | B3: LAPTOP MACKBOOK PRO 2021 - M1 PRO - 16GB | D3: GUSTI BAGUS - MEDIA | E3: JY9W0W424V | F3: ON | G3: YES | H3: Link | I3: 03 Juni 2023 | J3: IT SUPPORT - SYIDIQ
A4: 3 | B4: LAPTOP MACKBOOK PRO 2019 - i7 - 16GB | D4: YUDA SETIAWAN - MEDIA | E4: C02DWF0CMD6M | F4: ON | G4: YES | H4: Link | I4: 03 Juni 2023 | J4: IT SUPPORT - SYIDIQ
A5: 4 | B5: HP SAMSUNG GALAXY A12 | D5: SEKAR RAHMADANI KUMORONINGRUM | E5: RR8RC02KEDP | F5: ON | G5: YES | H5: Link | I5: 08 Juni 2023 | J5: IT SUPPORT - SYIDIQ
A6: 5 | B6: IMAC 24 SLV/8C CPU/8C GPU/8GB/512GB-ITP | C6: 007-B/III/2023 | D6: MEDIA TEAM | E6: C02JN1RRQ6W2 | F6: ON | G6: YES | I6: 09 Juni 2023 | J6: IT SUPPORT - SYIDIQ
A7: 7 | B7: IPHONE SE - BLACK | D7: SEKAR MEDIA TEAM | E7: FFMDF05BPMFK | F7: ON | G7: YES
A8: 8 | B8: HP SAMSUNG GALAXY A02 | D8: SEKAR MEDIA TEAM | E8: RR8RC0AH8QT | F8: ON | G8: YES
A9: 9
A10: 10
A11: 11
A12: 12
A13: 13
A14: 14
A15: 15
A16: 16
A17: 17
A18: 18
A19: 19
A20: 20
... A87: 87
A118: =IF(#REF!="","",A117+1) -> #REF!
A119: =IF(#REF!="","",A118+1) -> #REF!
A120: =IF(#REF!="","",A119+1) -> #REF!
A121: =IF(#REF!="","",A120+1) -> #REF!
A122: =IF(#REF!="","",A121+1) -> #REF!
A123: =IF(#REF!="","",A122+1) -> #REF!
A124: =IF(#REF!="","",A123+1) -> #REF!
A125: =IF(#REF!="","",A124+1) -> #REF!
A126: =IF(#REF!="","",A125+1) -> #REF!
A127: =IF(#REF!="","",A126+1) -> #REF!
A128: =IF(#REF!="","",A127+1) -> #REF!
A129: =IF(#REF!="","",A128+1) -> #REF!
... A985: =IF(#REF!="","",A984+1) -> #REF!

Sheet IT
A1: No | B1: Invent Name | C1: Code | D1: Use By | E1: Serial Number | F1: Condition | G1: Existence | H1: Image | I1: Update | J1: Updated By | K1: Note
A2: 1 | B2: LAPTOP DELL VOSTRO 3405 - R5 - 512GB - 8GB RAM | D2: M. SYIDIQ FAHRUL - IT SUPPORT | E2: 1YVTHK3 | F2: ON | G2: YES | I2: 03 Juni 2023 | J2: IT SUPPORT - SYIDIQ
A3: 2 | B3: LAPTOP MACKBOOK PRO 2013 - i7 - 8GB | D3: WIAN AGUS - IT DEVELOPMENT | E3: C02M61W7FD59 | F3: ON | G3: YES | I3: 03 Juni 2023 | J3: IT SUPPORT - SYIDIQ
A4: 3 | B4: HP SAMSUNG GALAXY A04 - BLACK | D4: ANDRE - MT IT | E4: R9CTB0432CN | F4: ON | G4: YES | I4: 07 Juni 2023 | J4: IT SUPPORT - SYIDIQ | K4: HP BARU
A5: 4 | B5: HP SAMSUNG GALAXY A04 - GREEN | D5: IT SUPPORT | E5: R9CW203LB0B | F5: ON | G5: YES | I5: 07 Juni 2023 | J5: IT SUPPORT - SYIDIQ | K5: HP BARU
A6: 5
A7: 6
A8: 7
A9: 8
A10: 9
A11: 10
A12: 11
A13: 12
A14: 13
A15: 14
A16: 15
A17: 16
... A88: 87
A119: =IF(#REF!="","",A118+1) -> #REF!
A120: =IF(#REF!="","",A119+1) -> #REF!
A121: =IF(#REF!="","",A120+1) -> #REF!
A122: =IF(#REF!="","",A121+1) -> #REF!
A123: =IF(#REF!="","",A122+1) -> #REF!
A124: =IF(#REF!="","",A123+1) -> #REF!
A125: =IF(#REF!="","",A124+1) -> #REF!
A126: =IF(#REF!="","",A125+1) -> #REF!
A127: =IF(#REF!="","",A126+1) -> #REF!
A128: =IF(#REF!="","",A127+1) -> #REF!
A129: =IF(#REF!="","",A128+1) -> #REF!
A130: =IF(#REF!="","",A129+1) -> #REF!
... A986: =IF(#REF!="","",A985+1) -> #REF!

Sheet CALL CENTER
A1: No | B1: Invent Name | C1: Code | D1: Use By | E1: Serial Number | F1: Condition | G1: Existence | H1: Image | I1: Update | J1: Updated By | K1: Note
A2: 1 | B2: DESKTIOP DELL INSPIRON ONE 2310 - i3 - 3GB | D2: YOYO KUSWOYO - CALL CENTER | E2: HYYX2P1 | F2: ON | G2: YES | H2: Link | I2: 08 Juni 2023 | J2: IT SUPPORT - SYIDIQ
A3: 2 | B3: DESKTOP GATEWAY ZX4930 - INTEL PENTIUM - 4GB | D3: NUR ALMAIDA MORREIRA / STEVANI AMALIA - CALL CENTER | E3: PWGBE02005115012573000 | F3: ON | G3: YES | H3: Link | I3: 08 Juni 2023 | J3: IT SUPPORT - SYIDIQ
A4: 3 | B4: DESKTOP GATEWAY ZX4930 - INTEL PENTIUM - 4GB | D4: ANANG DARMAWI - CALL CENTER | E4: PWGBE0200612900C223000 | F4: ON | G4: YES | H4: Link | I4: 08 Juni 2023 | J4: IT SUPPORT - SYIDIQ
A5: 4 | B5: HP IPHONE SE - WHITE | D5: CALL CENTER | E5: FFMDFPJ6PLJR | F5: ON | G5: YES | I5: 08 Juni 2023 | J5: IT SUPPORT - SYIDIQ
A6: 5 | B6: HP IPHONE 7 PLUS - BLACK | D6: CALL CENTER | E6: FYQX66F3HG04 | F6: ON | G6: YES | I6: 08 Juni 2023 | J6: IT SUPPORT - SYIDIQ
A7: 6
A8: 7
A9: 8
A10: 9
A11: 10
A12: 11
A13: 12
A14: 13
A15: 14
A16: 15
A17: 16
A18: 17
... A88: 87
A119: =IF(#REF!="","",A118+1) -> #REF!
A120: =IF(#REF!="","",A119+1) -> #REF!
A121: =IF(#REF!="","",A120+1) -> #REF!
A122: =IF(#REF!="","",A121+1) -> #REF!
A123: =IF(#REF!="","",A122+1) -> #REF!
A124: =IF(#REF!="","",A123+1) -> #REF!
A125: =IF(#REF!="","",A124+1) -> #REF!
A126: =IF(#REF!="","",A125+1) -> #REF!
A127: =IF(#REF!="","",A126+1) -> #REF!
A128: =IF(#REF!="","",A127+1) -> #REF!
A129: =IF(#REF!="","",A128+1) -> #REF!
A130: =IF(#REF!="","",A129+1) -> #REF!
... A986: =IF(#REF!="","",A985+1) -> #REF!

Sheet GA
A1: No | B1: Invent Name | C1: Code | D1: Use By | E1: Serial Number | F1: Condition | G1: Existence | H1: Image | I1: Update | J1: Updated By | K1: Note
A2: 1 | B2: HP SAMSUNG A13 - 4/128GB | C2: 005-B/VI/2023 | D2: GENERAL AFFAIR | E2: RR8T406Q9CR | F2: ON | G2: YES | H2: Link | I2: 07 Juni 2023 | J2: IT SUPPORT - SYIDIQ
A3: 2 | B3: DESKTOP GATEWAY - INTEL PENTIUM - 2GB | C3: SA-PND-IT/001/0051 | D3: GENERAL AFFAIR | E3: PWGBE02005109065823000 | F3: ON | G3: YES | H3: Link | I3: 07 Juni 2023 | J3: IT SUPPORT - SYIDIQ
A4: 3 | B4: DESKTOP GATEWAY - INTEL PENTIUM - 2GB | C4: SA-PND-IT/001/0076 | D4: GENERAL AFFAIR | E4: PWGBE020051150122A3000 | F4: ON | G4: YES | H4: Link | I4: 07 Juni 2023 | J4: IT SUPPORT - SYIDIQ | K4: EX ADMIN EXPAT
A5: 4 | B5: DESKTOP LENOVO IDEACENTRE B320 - i3 2120 - 4GB | C5: SA-PND-IT/001/0092 | D5: NADYA UMAROH / LESTI - STAF GA | E5: VS50055750 | F5: ON | G5: YES | H5: Link | I5: 07 Juni 2023 | J5: IT SUPPORT - SYIDIQ
A6: 5
A7: 6
A8: 7
A9: 8
A10: 9
A11: 10
A12: 11
A13: 12
A14: 13
A15: 14
A16: 15
A17: 16
... A88: 87
A119: =IF(#REF!="","",A118+1) -> #REF!
A120: =IF(#REF!="","",A119+1) -> #REF!
A121: =IF(#REF!="","",A120+1) -> #REF!
A122: =IF(#REF!="","",A121+1) -> #REF!
A123: =IF(#REF!="","",A122+1) -> #REF!
A124: =IF(#REF!="","",A123+1) -> #REF!
A125: =IF(#REF!="","",A124+1) -> #REF!
A126: =IF(#REF!="","",A125+1) -> #REF!
A127: =IF(#REF!="","",A126+1) -> #REF!
A128: =IF(#REF!="","",A127+1) -> #REF!
A129: =IF(#REF!="","",A128+1) -> #REF!
A130: =IF(#REF!="","",A129+1) -> #REF!
... A986: =IF(#REF!="","",A985+1) -> #REF!

Sheet DATA ANALYST
A1: No | B1: Invent Name | C1: Code | D1: Use By | E1: Serial Number | F1: Condition | G1: Existence | H1: Image | I1: Update | J1: Updated By | K1: Note
A2: 1 | B2: HP Pavilion 14-dv0517TX - RAM 16 GB | C2: 014-B/VI/2022 | D2: ALVIN PURNAMA DIHAR - DATA ANALYST | E2: 5CD1379V5K | F2: ON | G2: YES | I2: 07 Juni 2023 | J2: IT SUPPORT - SYIDIQ
A3: 2 | B3: DESKTOP LENOVO B320 - i3 - 6GB | D3: WAHYU DWI SAPUTRA - DATA ANALIYST | E3: VS20088321 | F3: ON | G3: YES | H3: Link | I3: 08 Juni 2023 | J3: IT SUPPORT - SYIDIQ
A4: 3 | B4: DESKTOP LENOVO B320 - i3 - 4GB | D4: PUSPUTA NURLAILA AP - DATA ANALIYST | E4: VS50056093 | F4: ON | G4: YES | H4: Link | I4: 08 Juni 2023 | J4: IT SUPPORT - SYIDIQ
A5: 4 | B5: DEKSTOP LENOVO 10102 - i3 - 8GB | C5: SA-PND-IT/001/0037 | D5: DIAN MARKUCI - DATA ANALYST | E5: VS80472108 | F5: ON | G5: YES | H5: Link | I5: 08 Juni 2023 | J5: IT SUPPORT - SYIDIQ
A6: 5
A7: 6
A8: 7
A9: 8
A10: 9
A11: 10
A12: 11
A13: 12
A14: 13
A15: 14
A16: 15
A17: 16
... A88: 87
A119: =IF(#REF!="","",A118+1) -> #REF!
A120: =IF(#REF!="","",A119+1) -> #REF!
A121: =IF(#REF!="","",A120+1) -> #REF!
A122: =IF(#REF!="","",A121+1) -> #REF!
A123: =IF(#REF!="","",A122+1) -> #REF!
A124: =IF(#REF!="","",A123+1) -> #REF!
A125: =IF(#REF!="","",A124+1) -> #REF!
A126: =IF(#REF!="","",A125+1) -> #REF!
A127: =IF(#REF!="","",A126+1) -> #REF!
A128: =IF(#REF!="","",A127+1) -> #REF!
A129: =IF(#REF!="","",A128+1) -> #REF!
A130: =IF(#REF!="","",A129+1) -> #REF!
... A986: =IF(#REF!="","",A985+1) -> #REF!

Sheet SAFETY
A1: No | B1: Invent Name | C1: Code | D1: Use By | E1: Serial Number | F1: Condition | G1: Existence | H1: Image | I1: Update | J1: Updated By | K1: Note
A2: 1 | B2: SAMSUNG GALAXY A04 | C2: 026-B-VI-2022 | D2: AMANDA - SAFETY | E2: R9CTA025GJX | F2: ON | G2: YES | H2: Link | I2: 45094 | J2: IT SUPPORT - SYIDIQ
A3: 2 | B3: Dell Vostro 3405 AMD R5 - 512GB - 8GB RAM | C3: 030-B/VI/2022 | D3: Amanda (Safety) | E3: 58KDYH3 | F3: ON | G3: YES | H3: Link | J3: IT SUPPORT - SYIDIQ
A4: 3 | B4: HP Pavilion 14-dv0517TX - RAM 16 GB | C4: 013-B/VI/2022 | D4: HILMAN - SAFETY | E4: 5CD1379VDD | F4: ON | G4: YES | H4: Link | J4: IT SUPPORT - SYIDIQ
A5: 4 | J5: IT SUPPORT - SYIDIQ
A6: 5 | J6: IT SUPPORT - SYIDIQ
A7: 6
A8: 7
A9: 8
A10: 9
A11: 10
A12: 11
A13: 12
A14: 13
A15: 14
A16: 15
A17: 16
A18: 17
... A88: 87
A119: =IF(#REF!="","",A118+1) -> #REF!
A120: =IF(#REF!="","",A119+1) -> #REF!
A121: =IF(#REF!="","",A120+1) -> #REF!
A122: =IF(#REF!="","",A121+1) -> #REF!
A123: =IF(#REF!="","",A122+1) -> #REF!
A124: =IF(#REF!="","",A123+1) -> #REF!
A125: =IF(#REF!="","",A124+1) -> #REF!
A126: =IF(#REF!="","",A125+1) -> #REF!
A127: =IF(#REF!="","",A126+1) -> #REF!
A128: =IF(#REF!="","",A127+1) -> #REF!
A129: =IF(#REF!="","",A128+1) -> #REF!
A130: =IF(#REF!="","",A129+1) -> #REF!
... A986: =IF(#REF!="","",A985+1) -> #REF!

Sheet Asset Entry
B3: Asset Entry & Update | I3: Today's Date | J3: =TODAY() -> 46285
C5: Building | D5: Floor | E5: Office/Room | F5: AC Type | G5: Condition | H5: Remarks
C6: Alvy | D6: Lantai 1 | E6: Dining Room B | F6: AC Central | G6: OFF | H6: Panas
B10: No | C10: Building | D10: Floor | E10: Office/Room | F10: AC Type | G10: Condition | H10: Remarks | I10: Last Updated
B11: =IF(C11="","",1)
B12: =IF(C12="","",B11+1)
B13: =IF(C13="","",B12+1)
B14: =IF(C14="","",B13+1)
B15: =IF(C15="","",B14+1)
B16: =IF(C16="","",B15+1)
B17: =IF(C17="","",B16+1)
B18: =IF(C18="","",B17+1)
B19: =IF(C19="","",B18+1)
B20: =IF(C20="","",B19+1)
B21: =IF(C21="","",B20+1)
B22: =IF(C22="","",B21+1)
B23: =IF(C23="","",B22+1)
... B1000: =IF(C1000="","",B999+1)

Sheet Entry Logs
A1: Building | B1: Floor | C1: Office | D1: AC Type | E1: Condition | F1: Remarks | G1: Timestamp
A2: Head Office | B2: Lantai 1 | C2: Ruang SQS Dept | D2: AC Central Daikin | E2: ON
A3: Head Office | B3: Lantai 1 | C3: Ruang Chief Operation & Chief Pilot | D3: AC Split Panasonic 1 Pk | E3: ON
A4: Head Office | B4: Lantai 1 | C4: Ruang FF & OCC Dept | D4: AC Split Panasonic 1 Pk | E4: ON
A5: Head Office | B5: Lantai 1 | C5: Ruang Call Centre & Data Analis Dept | D5: AC Central Daikin | E5: OFF | F5: Sudah agak dingin tapi masih panas
A6: Head Office | B6: Lantai 1 | C6: Ruang GA Dept | D6: AC Split Panasonic 1,5 Pk | E6: ON | F6: Berfungsi tapi timer terus menyala
A7: Head Office | B7: Lantai 2 | C7: Ruang HRD Dept | D7: AC Split Panasonic 3/4 Pk | E7: ON
A8: Head Office | B8: Lantai 2 | C8: Ruang Mba Nadine | D8: AC Split Panasonic 1 Pk | E8: ON
A9: Head Office | B9: Lantai 2 | C9: Ruang Perintis, Finance, Accounting A | D9: AC Central Daikin | E9: ON
A10: Head Office | B10: Lantai 2 | C10: Ruang Perintis, Finance, Accounting B | D10: AC Central Daikin | E10: OFF | F10: Outdoornya tidak ada
A11: Head Office | B11: Lantai 2 | C11: Ruang GA Storage | D11: AC Split Panasonic 1 Pk | E11: OFF
A12: Head Office | B12: Lantai 3 | C12: Ruang Meeting | D12: AC Split Panasonic 2 Pk | E12: ON
A13: Head Office | B13: Lantai 3 | C13: Ruang Legal, travel, Charter, Secretary | D13: AC Split Panasonic 1 Pk | E13: ON
A14: Head Office | B14: Lantai 3 | C14: Ruang Pak Geoffrey | D14: AC Split Panasonic 1 Pk | E14: ON
A15: Training | B15: Lantai 2 | C15: Ruang Training Dept | D15: AC Split Panasonic 1,5 Pk | E15: ON
A16: Training | B16: Lantai 2 | C16: Ruang Batch 4 | D16: AC Split Panasonic 1,5 Pk | E16: ON | F16: Berfungsi tapi kurang dingin
A17: Training | B17: Lantai 2 | C17: Ruang Kelas Pilot | D17: AC Split Panasonic 1,5 Pk | E17: ON
A18: PH | B18: Lantai 1 | C18: Ruang Simulator A | D18: AC Central Daikin | F18: Outdoor perlu diganti
A19: PH | B19: Lantai 1 | C19: Ruang Simulator B | D19: AC Central Daikin | F19: Outdoor perlu diganti
A20: PH | B20: Lantai 2 | C20: Ruang Papua (Media) | D20: AC Split Daikin | E20: ON
A21: PH | B21: Lantai 2 | C21: Ruang Kalimantan | D21: AC Split | E21: OFF
A22: PH | B22: Lantai 3 | C22: Ruang Gudang Ibu A | D22: AC Split | E22: ON
A23: PH | B23: Lantai 3 | C23: Ruang Gudang Ibu B | D23: AC Split | E23: ON
A24: PH | B24: Lantai 4 | C24: Ruang Gudang Ibu C | D24: AC Split | E24: ON
A25: PH | B25: Lantai 1 | C25: Ruang Brefing di Simulator A | D25: AC Split | E25: ON | F25: AC kurang dingin
A26: PH | B26: Lantai 1 | C26: Ruang Brefing di Simulator B | D26: AC Split | E26: ON | F26: AC kurang dingin
A27: Armand | B27: Lantai 1 | C27: Kamar Nomor 1 | D27: AC Split | E27: OFF
A28: Armand | B28: Lantai 1 | C28: Kamar Nomor 2 | D28: AC Split | E28: OFF
A29: Armand | B29: Lantai 1 | C29: Kamar Nomor 3 | D29: AC Split | E29: OFF
A30: Armand | B30: Lantai 1 | C30: Kamar Nomor 4 | D30: AC Split | E30: ON | F30: Suka bocor dan kurang dingin
A31: Armand | B31: Lantai 1 | C31: Kamar Nomor 7 | D31: AC Split | E31: OFF
A32: Armand | B32: Lantai 1 | C32: Kamar Nomor 9 | D32: AC Split | F32: Outdoor perlu diganti
A33: Armand | B33: Lantai 1 | C33: Kamar Nomor 11 | D33: AC Split | F33: Outdoor perlu diganti
A34: Armand | B34: Lantai 1 | C34: Kamar Nomor 12 | D34: AC Split | F34: Outdoor perlu diganti
A35: Armand | B35: Lantai 2 | C35: Kamar Nomor 19 | D35: AC Split | E35: ON | F35: Kurang dingin
A36: Armand | B36: Lantai 2 | C36: Kamar Nomor 20 | D36: AC Split | E36: ON | F36: AC panas dan suka bocor
A37: Armand | B37: Lantai 2 | C37: Kamar Nomor 21 | D37: AC Split | E37: ON | F37: Sering mati nyala & ga dingin
A38: Armand | B38: Lantai 3 | C38: Kamar Nomor 25 | D38: AC Split | E38: ON | F38: Ga dingin sering mati nyala
A39: Armand | B39: Lantai 3 | C39: Kamar Nomor 30 | D39: AC Split | E39: ON | F39: Ga dingin
A40: Armand | B40: Lantai 3 | C40: Kamar Nomor 31 | D40: AC Split | E40: ON | F40: Ga dingin
A41: Armand | B41: Lantai 3 | C41: Kamar Nomor 33 | D41: AC Split | E41: OFF
A42: Armand | B42: Lantai 3 | C42: Kamar Nomor 36 | D42: AC Split | E42: ON | F42: Suka kurang dingin
A43: Armand | B43: Lantai 1 | C43: Kamar Nomor 5 | D43: AC Split | E43: ON
A44: Armand | B44: Lantai 1 | C44: Kamar Nomor 6 | D44: AC Split | E44: ON
A45: Armand | B45: Lantai 1 | C45: Kamar Nomor 7 | D45: AC Split | E45: OFF
A46: Armand | B46: Lantai 1 | C46: Kamar Nomor 8 | D46: AC Split | E46: ON
A47: Armand | B47: Lantai 1 | C47: Kamar Nomor 9 | D47: AC Split | F47: Outdoor perlu diganti
A48: Armand | B48: Lantai 1 | C48: Kamar Nomor 10 | D48: AC Split | E48: ON
A49: Armand | B49: Lantai 1 | C49: Kamar Nomor 11 | D49: AC Split | F49: Outdoor perlu diganti
A50: Armand | B50: Lantai 1 | C50: Kamar Nomor 12 | D50: AC Split | F50: Outdoor perlu diganti
A51: Armand | B51: Lantai 2 | C51: Kamar Nomor 13 | D51: AC Split | E51: ON
A52: Armand | B52: Lantai 2 | C52: Kamar Nomor 14 | D52: AC Split | E52: ON
A53: Armand | B53: Lantai 2 | C53: Kamar Nomor 15 | D53: AC Split | E53: ON
A54: Armand | B54: Lantai 2 | C54: Kamar Nomor 16 | D54: AC Split | E54: ON
A55: Armand | B55: Lantai 2 | C55: Kamar Nomor 17 | D55: AC Split | E55: ON
A56: Armand | B56: Lantai 2 | C56: Kamar Nomor 18 | D56: AC Split | E56: ON
A57: Armand | B57: Lantai 2 | C57: Kamar Nomor 19 | D57: AC Split | E57: ON | F57: Kurang dingin
A58: Armand | B58: Lantai 2 | C58: Kamar Nomor 20 | D58: AC Split | E58: ON | F58: AC panas dan suka bocor
A59: Armand | B59: Lantai 2 | C59: Kamar Nomor 21 | D59: AC Split | E59: ON | F59: Sering mati nyala & ga dingin
A60: Armand | B60: Lantai 2 | C60: Kamar Nomor 22 | D60: AC Split | E60: ON
A61: Armand | B61: Lantai 2 | C61: Kamar Nomor 23 | D61: AC Split | E61: ON
A62: Armand | B62: Lantai 2 | C62: Kamar Nomor 24 | D62: AC Split | E62: ON
A63: Armand | B63: Lantai 3 | C63: Kamar Nomor 25 | D63: AC Split | E63: ON | F63: Ga dingin sering mati nyala
A64: Armand | B64: Lantai 3 | C64: Kamar Nomor 26 | D64: AC Split | E64: ON
A65: Armand | B65: Lantai 3 | C65: Kamar Nomor 27 | D65: AC Split | E65: ON
A66: Armand | B66: Lantai 3 | C66: Kamar Nomor 28 | D66: AC Split | E66: ON
A67: Armand | B67: Lantai 3 | C67: Kamar Nomor 29 | D67: AC Split | E67: ON
A68: Armand | B68: Lantai 3 | C68: Kamar Nomor 30 | D68: AC Split | E68: ON | F68: Ga dingin
A69: Armand | B69: Lantai 3 | C69: Kamar Nomor 31 | D69: AC Split | E69: ON | F69: Ga dingin
A70: Armand | B70: Lantai 3 | C70: Kamar Nomor 32 | D70: AC Split | E70: ON
A71: Armand | B71: Lantai 3 | C71: Kamar Nomor 33 | D71: AC Split | E71: OFF
A72: Armand | B72: Lantai 3 | C72: Kamar Nomor 34 | D72: AC Split | E72: ON
A73: Armand | B73: Lantai 3 | C73: Kamar Nomor 35 | D73: AC Split | E73: ON
A74: Armand | B74: Lantai 3 | C74: Kamar Nomor 36 | D74: AC Split | E74: ON | F74: Suka kurang dingin
A75: Alvy | B75: Lantai 1 | C75: Meeting Room A | D75: AC Split | E75: ON | G75: 45062
A76: Alvy | B76: Lantai 1 | C76: Meeting Room B | D76: AC Central | E76: OFF | G76: 45062
A77: Alvy | B77: Lantai 1 | C77: Dining Room A | D77: AC Split | E77: ON | G77: 45062
A78: Alvy | B78: Lantai 1 | C78: Dining Room B | D78: AC Central | E78: OFF | G78: 45062
A79: Alvy | B79: Lantai 1 | C79: Kamar Nomor 2 | D79: AC Split | E79: ON | G79: 45062
A80: Alvy | B80: Lantai 1 | C80: Kamar Nomor 4 | D80: AC Split | E80: ON | F80: Timer nyala AC mati sendiri | G80: 45062
A81: Alvy | B81: Lantai 1 | C81: Kamar Nomor 6 | D81: AC Split | E81: ON | F81: Sering timer kedip | G81: 45062
A82: Alvy | B82: Lantai 1 | C82: Kamar Nomor 8 | D82: AC Split | E82: ON | F82: Sering timer kedip | G82: 45062
A83: Alvy | B83: Lantai 1 | C83: Kamar Nomor 10 | D83: AC Split | E83: ON | G83: 45062
A84: Alvy | B84: Lantai 1 | C84: Kamar Nomor 12 | D84: AC Split | E84: ON | F84: Sering timer kedip | G84: 45062
A85: Alvy | B85: Lantai 1 | C85: Kamar Nomor 14 | D85: AC Split | E85: ON | G85: 45062
A86: Alvy | B86: Lantai 2 | C86: Kamar Nomor 16 | D86: AC Split | E86: ON | G86: 45062
A87: Alvy | B87: Lantai 2 | C87: Kamar Nomor 18 | D87: AC Split | E87: ON | G87: 45062
A88: Alvy | B88: Lantai 2 | C88: Kamar Nomor 20 | D88: AC Split | E88: ON | G88: 45062
A89: Alvy | B89: Lantai 2 | C89: Kamar Nomor 22 | D89: AC Split | E89: ON | G89: 45062
A90: Alvy | B90: Lantai 2 | C90: Kamar Nomor 24 | D90: AC Split | E90: ON | G90: 45062
A91: Alvy | B91: Lantai 2 | C91: Kamar Nomor 26 | D91: AC Split | E91: ON | G91: 45062
A92: Alvy | B92: Lantai 2 | C92: Kamar Nomor 28 | D92: AC Split | E92: ON | F92: Timer nyala AC mati sendiri | G92: 45062
A93: Alvy | B93: Lantai 2 | C93: Kamar Nomor 32 | D93: AC Split | E93: ON | G93: 45062
A94: Alvy | B94: Lantai 2 | C94: Kamar Nomor 34 | D94: AC Split | E94: ON | G94: 45062
A95: Alvy | B95: Lantai 3 | C95: Kamar Nomor 36 | D95: AC Split | E95: ON | F95: Bocor AC | G95: 45062
A96: Alvy | B96: Lantai 3 | C96: Kamar Nomor 38 | D96: AC Split | E96: ON | G96: 45062
A97: Alvy | B97: Lantai 3 | C97: Kamar Nomor 40 | D97: AC Split | E97: ON | F97: Kurang dingin | G97: 45062
A98: Alvy | B98: Lantai 3 | C98: Kamar Nomor 42 | D98: AC Split | E98: ON | G98: 45062
A99: Alvy | B99: Lantai 3 | C99: Kamar Nomor 44 | D99: AC Split | E99: ON | F99: AC panas | G99: 45062
A100: Alvy | B100: Lantai 3 | C100: Kamar Nomor 46 | D100: AC Split | E100: ON | F100: AC suka panas | G100: 45062
...
